Workbook

Sheet Hoja1
A1: CUENTA | B1: NOMBRE CUENTA | C1: CC | D1: AUX | E1: PROVEEDOR | F1: DESCRIPCION
A2: 5-2-05-05-01 | B2: Combustible Vehículos | C2: 10400006 | D2: 77721980 | E2: =VLOOKUP(D2,AUX!$A$1:$B$732,2,0) -> COMERCIAL G Q LIMITADA | F2: F3/908474 COMERCIAL G Q LIMITADA/DIESEL
A3: 5-1-01-04-06 | B3: C Vta Servicio Fletes De Exportacion | C3: 10400001 | D3: 86966100 | E3: =VLOOKUP(D3,AUX!$A$1:$B$732,2,0) -> DHL EXPRESS (CHILE) LIMITADA | F3: F3/4162473 DHL EXPRESS/ HWB 1582325006
A4: 5-2-03-05-01 | B4: Insumos | C4: 10400001 | D4: 77113520 | E4: =VLOOKUP(D4,AUX!$A$1:$B$732,2,0) -> IMPORTADORA IMPRECIN LTDA | F4: F3/83497 IMPORTADORA IMPRECIN/CINTA TRASNF
A5: 5-2-03-05-01 | B5: Insumos | C5: 10400001 | D5: 77113520 | E5: =VLOOKUP(D5,AUX!$A$1:$B$732,2,0) -> IMPORTADORA IMPRECIN LTDA | F5: F3/83423 IMPORTADORA IMPRECIN/ETIQ SEMIBRILLO
A6: 5-1-01-01-06 | B6: C Vta De Cerezas (Exportación) | C6: 10400001 | D6: 76189592 | E6: =VLOOKUP(D6,AUX!$A$1:$B$732,2,0) -> AGRICOLA FRANCISCO JAVIER MEDINA ELGUETA EMPRESA INDIVIDUAL | F6: F3/324 AG FRANCISCO JAVIER MEDINA/CEREZA EXP
A7: 5-1-01-01-06 | B7: C Vta De Cerezas (Exportación) | C7: 10400001 | D7: 76189592 | E7: =VLOOKUP(D7,AUX!$A$1:$B$732,2,0) -> AGRICOLA FRANCISCO JAVIER MEDINA ELGUETA EMPRESA INDIVIDUAL | F7: F3/327 AG FRANCISCO JAVIER MEDINA/CEREZA EXP
A8: 5-1-01-01-06 | B8: C Vta De Cerezas (Exportación) | C8: 10400001 | D8: 76395975 | E8: =VLOOKUP(D8,AUX!$A$1:$B$732,2,0) -> AGRICOLA MAYOL CALVO LTDA. | F8: F3/454 AGRICOLA MAYOL CALVO/CEREZA EXP
A9: 5-1-01-01-06 | B9: C Vta De Cerezas (Exportación) | C9: 10400001 | D9: 76855017 | E9: =VLOOKUP(D9,AUX!$A$1:$B$732,2,0) -> AGRICOLA LUNCUMILLA PEREZ LIMITADA | F9: F3/11 AG LUNCUMILLA PEREZ/CEREZA EXP
A10: 5-1-01-01-06 | B10: C Vta De Cerezas (Exportación) | C10: 10400001 | D10: 77294769 | E10: =VLOOKUP(D10,AUX!$A$1:$B$732,2,0) -> Agricola Donar Dos SpA | F10: F3/228 Agricola Donar Dos/CEREZA EXP
A11: 5-1-01-01-06 | B11: C Vta De Cerezas (Exportación) | C11: 10400001 | D11: 77134018 | E11: =VLOOKUP(D11,AUX!$A$1:$B$732,2,0) -> COMERCIALIZADORA Y EXPORTADORA PERQUIN FRUIT LIMITADA | F11: F3/74 COMERC Y EXPORT PERQUIN FRUIT/CEREZA EXP
A12: 5-1-01-01-06 | B12: C Vta De Cerezas (Exportación) | C12: 10400001 | D12: 78099070 | E12: =VLOOKUP(D12,AUX!$A$1:$B$732,2,0) -> AGRICOLA PULLAMI LTDA | F12: F3/1985 Agricola Pullami/CEREZA EXP
A13: 5-1-01-01-06 | B13: C Vta De Cerezas (Exportación) | C13: 10400001 | D13: 52003845 | E13: =VLOOKUP(D13,AUX!$A$1:$B$732,2,0) -> AGRICOLA EL NARANJAL LIMITADA | F13: F3/103 AG EL NARANJAL/CEREZA EXP
... A6135: 5-2-05-05-01 | B6135: Combustible Vehículos | C6135: 10400001 | D6135: 99520000 | E6135: =VLOOKUP(D6135,AUX!$A$1:$B$732,2,0) -> COPEC S.A. | F6135: F3/29527027/COPEC S.A./DIESEL

Sheet AUX
A1: 10049133 | B1: HELI FRANCISCO CARRASCO URETA
A2: 10168443 | B2: Gabriel Eduardo Jimenez Martinelli
A3: 10290176 | B3: JANNETTE DEL CARMEN ARGOMEDO GALAZ
A4: 10300064 | B4: JUAN ALEXIS REYES SEGURA
A5: 10302821 | B5: MARINA DEL CARMEN SEPULVEDA BARAHONA
A6: 10460607 | B6: SEGUNDO AGENOR DEL CARMEN GONZALEZ ACEBEO
A7: 10460642 | B7: JOSE RODRIGO PAVEZ MORENO
A8: 10819504 | B8: JORGE RODRIGUEZ PALMA
A9: 11110454 | B9: ALBERTO DEL CARMEN PONCE FARIAS
A10: 11277519 | B10: HERNAN RIGOBERTO MUÑOZ REYES
A11: 11493368 | B11: JOSE GREGORIO FLORES MUNOZ
A12: 11523509 | B12: JUAN CARLOS BERRIOS DUARTE
... A728: 99594180 | B728: Puerto Terrestre Los Andes Sociedad Concesionaria S.A.
A729: EXPO054 | B729: FESTER & CO GMNH
A730: EXPO118 | B730: HillFresh International
A731: GRAZIANI | B731: GRAZIANI PACKAGING SRL
A732: IMP30 | B732: COOL CARRIERS AB
A733: EXPO720 | B733: LUIS GUZMAN ROJAS
A734: EXPO721 | B734: MIGUEL DIAZ RUBILAR
A735: EXPO722 | B735: ALEJANDRO GUTIERREZ BUSTAMANTE
A736: EXPO723 | B736: MAURICIO ANDRES ARDILES NUÑEZ
A737: EXPO724 | B737: LUIS GONZALEZ OSORIO
A738: EXPO725 | B738: JOEL JARPA OYARZO
A739: EXPO726 | B739: LUIS MIRANDA
A740: EXPO727 | B740: HUGO PATRICIO SOTO
... A760: PLA00127 | B760: JULIO CASTAÑEDA
B761: JESUS RODRIGO AGUIRRE RIQUELME
B762: GONZALO FLORES
B763: LUIS ALEJANDRO MANCILLA BARAHONA
B764: Miranda Reyes Manuel Arturo
B765: MARIA JOSE DE LA ASUNCION MOLLER DE BAEREMAECKER
B766: PAULINA DIAZ
B767: LUIS NICOLAS PEÑA VALENZUELA
B768: KATHERINE ROJAS JIMENEZ
B769: FRANCISCO SUAREZ
B770: ARIEL GALLEGUILLOS
B771: FRANCISCA ROCIO GONZALEZ PEREZ
B772: JOSSELYN DEL RIO NANCO
... B1240: PADILLA GAETE MIGUEL ANTONIO
