Workbook

Sheet Hoja1
A1: Número | B1: Fecha | C1: Tipo | D1: C.Costo | E1: P. Caja | F1: Código | G1: Proveedor | H1: Tipo | I1: Número | J1: Inst. Financiero | K1: Debe | L1: Haber | M1: Descripción
A2: 2-1-02-02-03 | C2: Proveedores Nacionales | D2: 00000000 | E2: 0000000000 | F2: 8433631 | G2: =+VLOOKUP(F2,Hoja2!$A:$B,2,0) -> JUAN ANTONIO LARA RETAMAL | H2: F4 | I2: 69 | J2: 00000000 | K2: 0 | L2: 500000 | M2: F4/69 JUAN ANTONIO LARA RETAMAL/TRANSPORTE PERSONAL
A3: 5-2-02-09-01 | C3: Movilización | D3: 11110001 | E3: 0000000000 | F3: 8433631 | G3: =+VLOOKUP(F3,Hoja2!$A:$B,2,0) -> JUAN ANTONIO LARA RETAMAL | H3: 00 | I3: 0 | J3: 00000000 | K3: 500000 | L3: 0 | M3: F4/69 JUAN ANTONIO LARA RETAMAL/TRANSPORTE PERSONAL
A4: 2-1-02-02-03 | C4: Proveedores Nacionales | D4: 00000000 | E4: 0000000000 | F4: 8433631 | G4: =+VLOOKUP(F4,Hoja2!$A:$B,2,0) -> JUAN ANTONIO LARA RETAMAL | H4: F4 | I4: 70 | J4: 00000000 | K4: 0 | L4: 690000 | M4: F4/70 JUAN ANTONIO LARA RETAMAL/TRANSPORTE PERSONAL
A5: 5-2-02-09-01 | C5: Movilización | D5: 11110001 | E5: 0000000000 | F5: 8433631 | G5: =+VLOOKUP(F5,Hoja2!$A:$B,2,0) -> JUAN ANTONIO LARA RETAMAL | H5: 00 | I5: 0 | J5: 00000000 | K5: 690000 | L5: 0 | M5: F4/70 JUAN ANTONIO LARA RETAMAL/TRANSPORTE PERSONAL
A6: 2-1-02-02-03 | C6: Proveedores Nacionales | D6: 00000000 | E6: 0000000000 | F6: 19043083 | G6: =+VLOOKUP(F6,Hoja2!$A:$B,2,0) -> JORGE ANTONIO VILLENA ROJAS | H6: F3 | I6: 92 | J6: 00000000 | K6: 0 | L6: 114240 | M6: F3/92 JORGE ANTONIO VILLENA ROJAS/ ARR EXCAVADORA
A7: 5-2-04-17-01 | C7: Servicio Arriendo Maquinaria | D7: 11110001 | E7: 0000000000 | F7: 19043083 | G7: =+VLOOKUP(F7,Hoja2!$A:$B,2,0) -> JORGE ANTONIO VILLENA ROJAS | H7: 00 | I7: 0 | J7: 00000000 | K7: 96000 | L7: 0 | M7: F3/92 JORGE ANTONIO VILLENA ROJAS/ ARR EXCAVADORA
A8: 2-1-02-02-03 | C8: Proveedores Nacionales | D8: 00000000 | E8: 0000000000 | F8: 19043083 | G8: =+VLOOKUP(F8,Hoja2!$A:$B,2,0) -> JORGE ANTONIO VILLENA ROJAS | H8: F3 | I8: 94 | J8: 00000000 | K8: 0 | L8: 719712 | M8: F3/94 JORGE ANTONIO VILLENA ROJAS/ARR EXCAVADORA
A9: 5-2-04-17-01 | C9: Servicio Arriendo Maquinaria | D9: 11110001 | E9: 0000000000 | F9: 19043083 | G9: =+VLOOKUP(F9,Hoja2!$A:$B,2,0) -> JORGE ANTONIO VILLENA ROJAS | H9: 00 | I9: 0 | J9: 00000000 | K9: 604800 | L9: 0 | M9: F3/94 JORGE ANTONIO VILLENA ROJAS/ARR EXCAVADORA
A10: 2-1-02-02-03 | C10: Proveedores Nacionales | D10: 00000000 | E10: 0000000000 | F10: 17185304 | G10: =+VLOOKUP(F10,Hoja2!$A:$B,2,0) -> MARCELO TORRES AYALA | H10: F3 | I10: 168 | J10: 00000000 | K10: 0 | L10: 952000 | M10: F3/168 MARCELO TORRES AYALA/ ARR TRACTOR/OC-876
A11: 5-2-04-17-01 | C11: Servicio Arriendo Maquinaria | D11: 11110001 | E11: 0000000000 | F11: 17185304 | G11: =+VLOOKUP(F11,Hoja2!$A:$B,2,0) -> MARCELO TORRES AYALA | H11: 00 | I11: 0 | J11: 00000000 | K11: 800000 | L11: 0 | M11: F3/168 MARCELO TORRES AYALA/ ARR TRACTOR/OC-876
A12: 2-1-02-02-03 | C12: Proveedores Nacionales | D12: 00000000 | E12: 0000000000 | F12: 17185304 | G12: =+VLOOKUP(F12,Hoja2!$A:$B,2,0) -> MARCELO TORRES AYALA | H12: F3 | I12: 169 | J12: 00000000 | K12: 0 | L12: 952000 | M12: F3/169 MARCELO TORRES AYALA/ ARR TRACTOR/OC-998
A13: 5-2-04-17-01 | C13: Servicio Arriendo Maquinaria | D13: 11110301 | E13: 0000000000 | F13: 17185304 | G13: =+VLOOKUP(F13,Hoja2!$A:$B,2,0) -> MARCELO TORRES AYALA | H13: 00 | I13: 0 | J13: 00000000 | K13: 800000 | L13: 0 | M13: F3/169 MARCELO TORRES AYALA/ ARR TRACTOR/OC-998
... A1048: 5-3-01-02-02 | C1048: Gastos Bancarios | D1048: 00000000 | E1048: 00000000 | F1048: 97036000 | G1048: =+VLOOKUP(F1048,Hoja2!$A:$B,2,0) -> BANCO SANTANDER | H1048: 00 | I1048: 0 | J1048: 00000000 | K1048: 12559 | L1048: 0 | M1048: F4/14459414 BANCO SANTANDER/COM MANTENCION PLAN

Sheet CW20260626C210
A1: COMPROBANTES INGRESADOS
A2: Moneda : 01 Peso Chileno
A3: Tipo : Todos
A4: Rango de Folios : Todos
A5: Fecha : 26/06/2026
A6: Norma: Tributaria e IFRS
A7: Area de Negocio: Todas
A9: Número | B9: Fecha | C9: Tipo | D9: N° Interno | E9: Estado | F9: Descripción
A10: Código Cuenta | C10: Descripción Cuenta | D10: Código | E10: Código | F10: Auxiliar | G10: Documento | I10: Det. de Gasto /
D11: C.Costo | E11: P. Caja | F11: Código | G11: Tipo | H11: Número | I11: Inst. Financiero | J11: Debe | K11: Haber | L11: Descripción
A13: 00000001 | B13: 01/01/2025 | C13: T | D13: 00000001 | E13: Vigente | F13: Reverso de cpbte. N° 00001908, año 2024. DIF TC UF CXP ACCIO
A14: 2-2-03-01-02 | C14: Cuentas Por Pagar Accionistas LP | D14: 00000000 | E14: 0000000000 | F14: 0000000000 | G14: 00 | H14: 0 | I14: 00000000 | J14: 59327301 | K14: 0 | L14: DIF TC UF CXP ACCIONISTA DIC.24
A15: 5-3-02-02-06 | C15: Diferencia de Cambio UF | D15: 00000000 | E15: 0000000000 | F15: 0000000000 | G15: 00 | H15: 0 | I15: 00000000 | J15: 0 | K15: 59327301 | L15: DIF TC UF CXP ACCIONISTA DIC.24
F17: Total Comprobante | J17: 59327301 | K17: 59327301
A19: 00000002 | B19: 01/01/2025 | C19: T | D19: 00000002 | E19: Vigente | F19: Reverso de cpbte. N° 00001903, año 2024. DIF TC ST DICIEMBRE
A20: 1-1-01-03-02 | C20: Banco Santander USD | D20: 00000000 | E20: 0000000000 | F20: 0000000000 | G20: DF | H20: 31122024 | I20: 00000000 | J20: 0 | K20: 420686 | L20: DIF TC ST DICIEMBRE 24
A21: 5-3-02-02-05 | C21: Diferencia de Cambio U$ | D21: 00000000 | E21: 0000000000 | F21: 0000000000 | G21: 00 | H21: 0 | I21: 00000000 | J21: 420686 | K21: 0 | L21: DIF TC ST DICIEMBRE 24
F23: Total Comprobante | J23: 420686 | K23: 420686
A25: 00000003 | B25: 01/01/2025 | C25: T | D25: 00000003 | E25: Vigente | F25: Reverso de cpbte. N° 00001909, año 2024. DIF TC UF DIC.24
A26: 2-2-04-01-16 | C26: CXP Soc Inv La Turbina | D26: 00000000 | E26: 0000000000 | F26: 0000000000 | G26: 00 | H26: 0 | I26: 00000000 | J26: 61406774 | K26: 0 | L26: DIF TC UF TURBINA DIC.24
A27: 2-2-04-01-17 | C27: CXP Soc Inv Centenario | D27: 00000000 | E27: 0000000000 | F27: 0000000000 | G27: 00 | H27: 0 | I27: 00000000 | J27: 61406774 | K27: 0 | L27: DIF TC UF CENTENARIO DIC.24
A28: 5-3-02-02-06 | C28: Diferencia de Cambio UF | D28: 00000000 | E28: 0000000000 | F28: 0000000000 | G28: 00 | H28: 0 | I28: 00000000 | J28: 0 | K28: 61406774 | L28: DIF TC UF TURBINA DIC.24
A29: 5-3-02-02-06 | C29: Diferencia de Cambio UF | D29: 00000000 | E29: 0000000000 | F29: 0000000000 | G29: 00 | H29: 0 | I29: 00000000 | J29: 0 | K29: 61406774 | L29: DIF TC UF CENTENARIO DIC.24
F31: Total Comprobante | J31: 122813548 | K31: 122813548
A33: 00000004 | B33: 17/01/2025 | C33: E | D33: 00000001 | E33: Vigente | F33: PAGO PROVEEDORES $9.010.129
A34: 2-1-02-02-03 | C34: Proveedores Nacionales | D34: 00000000 | E34: 0000000000 | F34: 17185304 | G34: CB | H34: 30072029 | I34: 00000000 | J34: 285600 | K34: 0 | L34: Pago: F3 157 | M34: MARCELO TORRES AYALA
A35: 2-1-02-02-03 | C35: Proveedores Nacionales | D35: 00000000 | E35: 0000000000 | F35: 17185304 | G35: CB | H35: 30072029 | I35: 00000000 | J35: 952000 | K35: 0 | L35: Pago: F3 159 | M35: MARCELO TORRES AYALA
A36: 2-1-02-02-03 | C36: Proveedores Nacionales | D36: 00000000 | E36: 0000000000 | F36: 17185304 | G36: CB | H36: 30072029 | I36: 00000000 | J36: 160650 | K36: 0 | L36: Pago: F3 160 | M36: MARCELO TORRES AYALA
A37: 2-1-02-02-03 | C37: Proveedores Nacionales | D37: 00000000 | E37: 0000000000 | F37: 76307645 | G37: CB | H37: 30072029 | I37: 00000000 | J37: 257007 | K37: 0 | L37: Pago: F3 465673 | M37: INVERSIONES Y COMERCIAL VICHUQUEN SPA
A38: 2-1-02-02-03 | C38: Proveedores Nacionales | D38: 00000000 | E38: 0000000000 | F38: 76488070 | G38: CB | H38: 30072029 | I38: 00000000 | J38: 142705 | K38: 0 | L38: Pago: F3 890355 | M38: INGENIERIA Y SEGURIDAD INDUSTRIAL KS LTDA
A39: 2-1-02-02-03 | C39: Proveedores Nacionales | D39: 00000000 | E39: 0000000000 | F39: 76488070 | G39: CB | H39: 30072029 | I39: 00000000 | J39: 95152 | K39: 0 | L39: Pago: F3 890557 | M39: INGENIERIA Y SEGURIDAD INDUSTRIAL KS LTDA
A40: 2-1-02-02-03 | C40: Proveedores Nacionales | D40: 00000000 | E40: 0000000000 | F40: 76604898 | G40: CB | H40: 30072029 | I40: 00000000 | J40: 131044 | K40: 0 | L40: Pago: F3 6196 | M40: TECNOLOGÍAS EN SEGURIDAD LIMITADA
A41: 2-1-02-02-03 | C41: Proveedores Nacionales | D41: 00000000 | E41: 0000000000 | F41: 76604898 | G41: CB | H41: 30072029 | I41: 00000000 | J41: 132038 | K41: 0 | L41: Pago: F3 6323 | M41: TECNOLOGÍAS EN SEGURIDAD LIMITADA
A42: 2-1-02-02-03 | C42: Proveedores Nacionales | D42: 00000000 | E42: 0000000000 | F42: 76655211 | G42: CB | H42: 30072029 | I42: 00000000 | J42: 499800 | K42: 0 | L42: Pago: F3 9367 | M42: SOCIEDAD COMERCIAL ALESAN LTDA
A43: 2-1-02-02-03 | C43: Proveedores Nacionales | D43: 00000000 | E43: 0000000000 | F43: 76895010 | G43: CB | H43: 30072029 | I43: 00000000 | J43: 442707 | K43: 0 | L43: Pago: F3 8448 | M43: SERVI RIEGO S.A.
A44: 2-1-02-02-03 | C44: Proveedores Nacionales | D44: 00000000 | E44: 0000000000 | F44: 76895010 | G44: CB | H44: 30072029 | I44: 00000000 | J44: 2118200 | K44: 0 | L44: Pago: F3 8454 | M44: SERVI RIEGO S.A.
A45: 2-1-02-02-03 | C45: Proveedores Nacionales | D45: 00000000 | E45: 0000000000 | F45: 76895010 | G45: CB | H45: 30072029 | I45: 00000000 | J45: 649306 | K45: 0 | L45: Pago: F3 8509 | M45: SERVI RIEGO S.A.
... A55: 1-1-01-02-02 | C55: Banco Santander $ | D55: 00000000 | E55: 0000000000 | F55: 0000000000 | G55: CB | H55: 17012025 | I55: 00000000 | J55: 0 | K55: 9010129 | L55: CB 30072029 | M55: Pago varios proveedores
F57: Total Comprobante | J57: 9010129 | K57: 9010129
A59: 00000005 | B59: 10/01/2025 | C59: T | D59: 00000004 | E59: Vigente | F59: F4/69/JUAN ANTONIO LARA RETAMAL
A60: 2-1-02-02-03 | C60: Proveedores Nacionales | D60: 00000000 | E60: 0000000000 | F60: 8433631 | G60: F4 | H60: 69 | I60: 00000000 | J60: 0 | K60: 500000 | L60: F4/69 JUAN ANTONIO LARA RETAMAL/TRANSPORTE PERSONAL
A61: 5-2-02-09-01 | C61: Movilización | D61: 11110001 | E61: 0000000000 | F61: 0000000000 | G61: 00 | H61: 0 | I61: 00000000 | J61: 500000 | K61: 0 | L61: F4/69 JUAN ANTONIO LARA RETAMAL/TRANSPORTE PERSONAL
F63: Total Comprobante | J63: 500000 | K63: 500000
A65: 00000006 | B65: 10/01/2025 | C65: T | D65: 00000005 | E65: Vigente | F65: F4/70/JUAN ANTONIO LARA RETAMAL
A66: 2-1-02-02-03 | C66: Proveedores Nacionales | D66: 00000000 | E66: 0000000000 | F66: 8433631 | G66: F4 | H66: 70 | I66: 00000000 | J66: 0 | K66: 690000 | L66: F4/70 JUAN ANTONIO LARA RETAMAL/TRANSPORTE PERSONAL
A67: 5-2-02-09-01 | C67: Movilización | D67: 11110001 | E67: 0000000000 | F67: 0000000000 | G67: 00 | H67: 0 | I67: 00000000 | J67: 690000 | K67: 0 | L67: F4/70 JUAN ANTONIO LARA RETAMAL/TRANSPORTE PERSONAL
F69: Total Comprobante | J69: 690000 | K69: 690000
A71: 00000007 | B71: 10/01/2025 | C71: T | D71: 00000006 | E71: Vigente | F71: F3/92/JORGE ANTONIO VILLENA ROJAS
A72: 2-1-02-02-03 | C72: Proveedores Nacionales | D72: 00000000 | E72: 0000000000 | F72: 19043083 | G72: F3 | H72: 92 | I72: 00000000 | J72: 0 | K72: 114240 | L72: F3/92 JORGE ANTONIO VILLENA ROJAS/ ARR EXCAVADORA
A73: 1-1-07-01-01 | C73: IVA Crédito Fiscal | D73: 00000000 | E73: 0000000000 | F73: 0000000000 | G73: 00 | H73: 0 | I73: 00000000 | J73: 18240 | K73: 0 | L73: F3/92 JORGE ANTONIO VILLENA ROJAS/ ARR EXCAVADORA
A74: 5-2-04-17-01 | C74: Servicio Arriendo Maquinaria | D74: 11110001 | E74: 0000000000 | F74: 0000000000 | G74: 00 | H74: 0 | I74: 00000000 | J74: 96000 | K74: 0 | L74: F3/92 JORGE ANTONIO VILLENA ROJAS/ ARR EXCAVADORA
F76: Total Comprobante | J76: 114240 | K76: 114240
A78: 00000008 | B78: 10/01/2025 | C78: T | D78: 00000007 | E78: Vigente | F78: F3/94/JORGE ANTONIO VILLENA ROJAS
A79: 2-1-02-02-03 | C79: Proveedores Nacionales | D79: 00000000 | E79: 0000000000 | F79: 19043083 | G79: F3 | H79: 94 | I79: 00000000 | J79: 0 | K79: 719712 | L79: F3/94 JORGE ANTONIO VILLENA ROJAS/ARR EXCAVADORA
A80: 1-1-07-01-01 | C80: IVA Crédito Fiscal | D80: 00000000 | E80: 0000000000 | F80: 0000000000 | G80: 00 | H80: 0 | I80: 00000000 | J80: 114912 | K80: 0 | L80: F3/94 JORGE ANTONIO VILLENA ROJAS/ARR EXCAVADORA
A81: 5-2-04-17-01 | C81: Servicio Arriendo Maquinaria | D81: 11110001 | E81: 0000000000 | F81: 0000000000 | G81: 00 | H81: 0 | I81: 00000000 | J81: 604800 | K81: 0 | L81: F3/94 JORGE ANTONIO VILLENA ROJAS/ARR EXCAVADORA
F83: Total Comprobante | J83: 719712 | K83: 719712
A85: 00000009 | B85: 10/01/2025 | C85: T | D85: 00000008 | E85: Vigente | F85: F3/168/MARCELO TORRES AYALA
A86: 2-1-02-02-03 | C86: Proveedores Nacionales | D86: 00000000 | E86: 0000000000 | F86: 17185304 | G86: F3 | H86: 168 | I86: 00000000 | J86: 0 | K86: 952000 | L86: F3/168 MARCELO TORRES AYALA/ ARR TRACTOR/OC-876
A87: 1-1-07-01-01 | C87: IVA Crédito Fiscal | D87: 00000000 | E87: 0000000000 | F87: 0000000000 | G87: 00 | H87: 0 | I87: 00000000 | J87: 152000 | K87: 0 | L87: F3/168 MARCELO TORRES AYALA/ ARR TRACTOR/OC-876
A88: 5-2-04-17-01 | C88: Servicio Arriendo Maquinaria | D88: 11110001 | E88: 0000000000 | F88: 0000000000 | G88: 00 | H88: 0 | I88: 00000000 | J88: 800000 | K88: 0 | L88: F3/168 MARCELO TORRES AYALA/ ARR TRACTOR/OC-876
F90: Total Comprobante | J90: 952000 | K90: 952000
A92: 00000010 | B92: 10/01/2025 | C92: T | D92: 00000009 | E92: Vigente | F92: F3/169/MARCELO TORRES AYALA
A93: 2-1-02-02-03 | C93: Proveedores Nacionales | D93: 00000000 | E93: 0000000000 | F93: 17185304 | G93: F3 | H93: 169 | I93: 00000000 | J93: 0 | K93: 952000 | L93: F3/169 MARCELO TORRES AYALA/ ARR TRACTOR/OC-998
A94: 1-1-07-01-01 | C94: IVA Crédito Fiscal | D94: 00000000 | E94: 0000000000 | F94: 0000000000 | G94: 00 | H94: 0 | I94: 00000000 | J94: 152000 | K94: 0 | L94: F3/169 MARCELO TORRES AYALA/ ARR TRACTOR/OC-998
A95: 5-2-04-17-01 | C95: Servicio Arriendo Maquinaria | D95: 11110301 | E95: 0000000000 | F95: 0000000000 | G95: 00 | H95: 0 | I95: 00000000 | J95: 800000 | K95: 0 | L95: F3/169 MARCELO TORRES AYALA/ ARR TRACTOR/OC-998
F97: Total Comprobante | J97: 952000 | K97: 952000
A99: 00000011 | B99: 10/01/2025 | C99: T | D99: 00000010 | E99: Vigente | F99: F3/170/MARCELO TORRES AYALA
A100: 2-1-02-02-03 | C100: Proveedores Nacionales | D100: 00000000 | E100: 0000000000 | F100: 17185304 | G100: F3 | H100: 170 | I100: 00000000 | J100: 0 | K100: 952000 | L100: F3/170 MARCELO TORRES AYALA/ ARR NEBULIZADOR/OC-999
A101: 1-1-07-01-01 | C101: IVA Crédito Fiscal | D101: 00000000 | E101: 0000000000 | F101: 0000000000 | G101: 00 | H101: 0 | I101: 00000000 | J101: 152000 | K101: 0 | L101: F3/170 MARCELO TORRES AYALA/ ARR NEBULIZADOR/OC-999
A102: 5-2-04-19-01 | C102: Servicio Arriendo Equipos | D102: 11110301 | E102: 0000000000 | F102: 0000000000 | G102: 00 | H102: 0 | I102: 00000000 | J102: 800000 | K102: 0 | L102: F3/170 MARCELO TORRES AYALA/ ARR NEBULIZADOR/OC-999
F104: Total Comprobante | J104: 952000 | K104: 952000
A106: 00000012 | B106: 10/01/2025 | C106: T | D106: 00000011 | E106: Vigente | F106: F3/720/CARMEN LUISA SCHADE YANKOVIC
A107: 2-1-02-02-03 | C107: Proveedores Nacionales | D107: 00000000 | E107: 0000000000 | F107: 9418583 | G107: F3 | H107: 720 | I107: 00000000 | J107: 0 | K107: 163030 | L107: F3/720 CARMEN LUISA SCHADE YANKOVIC/RETIRO ENVASES/OC-1124
A108: 1-1-07-01-01 | C108: IVA Crédito Fiscal | D108: 00000000 | E108: 0000000000 | F108: 0000000000 | G108: 00 | H108: 0 | I108: 00000000 | J108: 26030 | K108: 0 | L108: F3/720 CARMEN LUISA SCHADE YANKOVIC/RETIRO ENVASES/OC-1124
A109: 5-2-04-07-01 | C109: Servicio de Aseo | D109: 11110001 | E109: 0000000000 | F109: 0000000000 | G109: 00 | H109: 0 | I109: 00000000 | J109: 137000 | K109: 0 | L109: F3/720 CARMEN LUISA SCHADE YANKOVIC/RETIRO ENVASES/OC-1124
F111: Total Comprobante | J111: 163030 | K111: 163030
A113: 00000013 | B113: 10/01/2025 | C113: T | D113: 00000012 | E113: Vigente | F113: F3/6473/TECNOLOGÍAS EN SEGURIDAD LIMITADA
A114: 2-1-02-02-03 | C114: Proveedores Nacionales | D114: 00000000 | E114: 0000000000 | F114: 76604898 | G114: F3 | H114: 6473 | I114: 00000000 | J114: 0 | K114: 132585 | L114: F3/6473 TECNOLOGÍAS EN SEGURIDAD/SERVICIO ALPHA
A115: 1-1-07-01-01 | C115: IVA Crédito Fiscal | D115: 00000000 | E115: 0000000000 | F115: 0000000000 | G115: 00 | H115: 0 | I115: 00000000 | J115: 21169 | K115: 0 | L115: F3/6473 TECNOLOGÍAS EN SEGURIDAD/SERVICIO ALPHA
A116: 5-2-04-09-01 | C116: Seguridad | D116: 11110001 | E116: 0000000000 | F116: 0000000000 | G116: 00 | H116: 0 | I116: 00000000 | J116: 111416 | K116: 0 | L116: F3/6473 TECNOLOGÍAS EN SEGURIDAD/SERVICIO ALPHA
F118: Total Comprobante | J118: 132585 | K118: 132585
A120: 00000014 | B120: 10/01/2025 | C120: T | D120: 00000013 | E120: Vigente | F120: F3/6886/RINCÓN FERRETERO SPA
A121: 2-1-02-02-03 | C121: Proveedores Nacionales | D121: 00000000 | E121: 0000000000 | F121: 76975156 | G121: F3 | H121: 6886 | I121: 00000000 | J121: 0 | K121: 5480 | L121: F3/6886 RINCÓN FERRETERO/HEMBRA 10
A122: 1-1-07-01-01 | C122: IVA Crédito Fiscal | D122: 00000000 | E122: 0000000000 | F122: 0000000000 | G122: 00 | H122: 0 | I122: 00000000 | J122: 875 | K122: 0 | L122: F3/6886 RINCÓN FERRETERO/HEMBRA 10
A123: 5-2-03-05-01 | C123: Insumos | D123: 11110001 | E123: 0000000000 | F123: 0000000000 | G123: 00 | H123: 0 | I123: 00000000 | J123: 4605 | K123: 0 | L123: F3/6886 RINCÓN FERRETERO/HEMBRA 10
F125: Total Comprobante | J125: 5480 | K125: 5480
A127: 00000015 | B127: 10/01/2025 | C127: T | D127: 00000014 | E127: Vigente | F127: F3/44148/TOM PETROL SPA
A128: 2-1-02-02-03 | C128: Proveedores Nacionales | D128: 00000000 | E128: 0000000000 | F128: 76397190 | G128: F3 | H128: 44148 | I128: 00000000 | J128: 0 | K128: 980000 | L128: F3/44148 TOM PETROL/ DIESEL
A129: 1-1-07-01-01 | C129: IVA Crédito Fiscal | D129: 00000000 | E129: 0000000000 | F129: 0000000000 | G129: 00 | H129: 0 | I129: 00000000 | J129: 146252 | K129: 0 | L129: F3/44148 TOM PETROL/ DIESEL
A130: 1-1-08-01-02 | C130: Materiales e Insumos | D130: 00000000 | E130: 0000000000 | F130: 0000000000 | G130: 00 | H130: 0 | I130: 00000000 | J130: 769748 | K130: 0 | L130: F3/44148 TOM PETROL/ DIESEL
A131: 1-1-07-01-02 | C131: Impto. Petróleo Diésel (Ley 18.502) | D131: 00000000 | E131: 0000000000 | F131: 0000000000 | G131: 00 | H131: 0 | I131: 00000000 | J131: 64000 | K131: 0 | L131: F3/44148 TOM PETROL/ DIESEL
F133: Total Comprobante | J133: 980000 | K133: 980000
A135: 00000016 | B135: 10/01/2025 | C135: T | D135: 00000015 | E135: Vigente | F135: F3/44170/TOM PETROL SPA
A136: 2-1-02-02-03 | C136: Proveedores Nacionales | D136: 00000000 | E136: 0000000000 | F136: 76397190 | G136: F3 | H136: 44170 | I136: 00000000 | J136: 0 | K136: 1470000 | L136: F3/44170 TOM PETROL/ DIESEL
A137: 1-1-07-01-01 | C137: IVA Crédito Fiscal | D137: 00000000 | E137: 0000000000 | F137: 0000000000 | G137: 00 | H137: 0 | I137: 00000000 | J137: 219378 | K137: 0 | L137: F3/44170 TOM PETROL/ DIESEL
A138: 1-1-08-01-02 | C138: Materiales e Insumos | D138: 00000000 | E138: 0000000000 | F138: 0000000000 | G138: 00 | H138: 0 | I138: 00000000 | J138: 1154622 | K138: 0 | L138: F3/44170 TOM PETROL/ DIESEL
A139: 1-1-07-01-02 | C139: Impto. Petróleo Diésel (Ley 18.502) | D139: 00000000 | E139: 0000000000 | F139: 0000000000 | G139: 00 | H139: 0 | I139: 00000000 | J139: 96000 | K139: 0 | L139: F3/44170 TOM PETROL/ DIESEL
F141: Total Comprobante | J141: 1470000 | K141: 1470000
A143: 00000017 | B143: 10/01/2025 | C143: T | D143: 00000016 | E143: Vigente | F143: F6/658078/TATTERSALL AGROINSUMOS S.A.
...

Sheet Hoja2
A1: Código | B1: Razón social
A2: 10049125 | B2: JOSE SANDRO CARRASCO URETA
A3: 10105483 | B3: JOSE CELSO DIAZ GONZALEZ
A4: 10174283 | B4: LEOPOLDO ANTONIO URRA CONTRERAS
A5: 10214530 | B5: GERARDO RAMIRO AMARO ROJAS
A6: 10300064 | B6: JUAN ALEXIS REYES SEGURA
A7: 10302821 | B7: MARINA DEL CARMEN SEPULVEDA BARAHONA
A8: 10347469 | B8: PABLO MAGNASO VASQUEZ
A9: 10386651 | B9: ROSAMEL FERNANDEZ BLANCO
A10: 10438993 | B10: EDUARDO ANTONIO NUNEZ JEREZ
A11: 10460349 | B11: DANILO ESTEBAN PINCHEIRA MORALES
A12: 10483031 | B12: ALEJANDRO RODRIGO ARAYA PACHECO
A13: 10626535 | B13: OSCAR RODOLFO ROJAS ARRIAGADA
... A15: 10920668 | B15: CAMILA JORQUIERA
A16: 10927072CT | B16: PAOLA ANDREA ESCOBAR BURGOS
A17: 10940143CT | B17: MARIA LUISA PONCE SEPULVEDA
A18: 10975553 | B18: CLAUDIA MATUS GATICA
A19: 11277519 | B19: Hernan Rigoberto Muñoz Reyes
A20: 11283655 | B20: LUIS IVAN CORDERO CASTRO
A21: 11284640 | B21: ROBERTO ANTONIO NUÑEZ LEIVA
A22: 11372481 | B22: JOSE SAAVEDRA VASQUEZ
A23: 11457402 | B23: LUIS ORLANDO ALBORNOZ MUÑOZ
A24: 11472336 | B24: SERGIO GUZMAN LARRAIN
A25: 11528751 | B25: JOSE HERNAN PLAZA GALLARDO
A26: 11554940 | B26: LUIS GUILLERMO PEÑA VALDES
A27: 11562253 | B27: MARIA INES FAUNDEZ GUAJARDO
A28: 11562337 | B28: CARMEN JIMENA SEPULVEDA MORENO
A29: 11676150 | B29: ALICIA DEL CARMEN VILLAGRA LUPAYANTE
... A45: 12587598 | B45: MAURICIO GRACIA RAMIREZ
A46: 12725734CT | B46: SUSSY ALEJANDRA ASTORGA RIVERAS
A47: 12725773 | B47: MAXIMILIANO FABIAN FLORES ARAYA
A48: 12725936 | B48: CLAUDIA ANDREA REYES SEGURA
A49: 12783019 | B49: PEDRO VIDAL MOYA DIAZ
A50: 12787535 | B50: DAVID TEJO CIFUENTES
A51: 12883789 | B51: LUIS IGNACIO MANQUEHUAL
A52: 12912271 | B52: RODRIGO ALFONSO ALARCON CORRALES
A53: 12963368 | B53: PABLO ANDRES CONTRERAS VASQUEZ
A54: 13051415 | B54: JULIAN ANDRES MIRANDA OSSES
A55: 13053998 | B55: CYNTHIA FRANCESCA ALVEAR HENRIQUEZ
A56: 13100069 | B56: CARLOS ECHAGUE PAVEZ
A57: 13100102 | B57: AMERICO ZUÑIGA
A58: 13304822 | B58: JOSE NAVARRETE GONZALEZ
... A146: 19210510 | B146: Carlos Moreno Labra
A147: 19210510CT | B147: CARLOS FELIPE MORENO LABRA
A148: 19472601 | B148: BARBARA CACERES BRAVO
A149: 19474265 | B149: SEBASTIAN RAMIREZ
A150: 19527120 | B150: Alejandro Antonio Acevedo Zuñiga
A151: 19656953 | B151: EDUARDO BIERE CONTRERAS
A152: 19749814 | B152: JOSE ARAYA CATALAN
A153: 20024951 | B153: CAROLINA MUÑOZ ESPINOZA
A154: 21016969 | B154: NELSON MEDEL PINCHEIRA
A155: 21626600 | B155: EDILIA PATRICIA ROJAS GUTIERREZ
A156: 3611018 | B156: HUGO NAJLE HAYE
A157: 4457613 | B157: ANATOLIO JOSE DEL CARMEN RAMIREZ VALENZUELA
A158: 4458456 | B158: MARIA ANGELICA FARIAS LOPEZ
A159: 4617846 | B159: MIGUEL ANTONIO LARA MORALES
... A207: 76031716 | B207: Tivar Helicopteros Spa
A208: 76033621CT | B208: AGRICOLA Y COMERCIAL EL TREBOL SPA
A209: 76039218 | B209: SERVICIO ADR LTDA.
A210: 76040476 | B210: COMERCIALIZADORA VIVERO CORCOLEN
A211: 76042831 | B211: AGRISERVICE SPA
A212: 76045220 | B212: Sociedad comercial agrinet Ltda.
A213: 76045512 | B213: BESTPLANT SPA
A214: 76046809 | B214: DAP DUCASSE DISEÑO LTDA
A215: 76046889 | B215: MARTINEZ Y VALDIVIESO S.A
A216: 76048145 | B216: COMERCIALIZADORA DE ENVASES INDUSTRIALES LIMITADASUPERBIDON
A217: 76051243 | B217: COMERCIAL HIDRAULICA RESTOCK LTDA.
A218: 76052927 | B218: Soc. Conc. Autopista Nueva Vespucio Sur S.A.
A219: 76053627 | B219: BS PRODUCCIONES E INVERSIONES LIMITADA
A220: 76061483 | B220: SOCIEDAD DE SERVICIOS PIA Y COMPANIA LIMITADA
... A421: 76921928 | B421: AGROUTIL MARIA JOSE UGARTE TAPIA E.I.R.L.
A422: 76921928CT | B422: AGROUTIL MARIA JOSE UGARTE TAPIA E.I.R.L.
A423: 76923540 | B423: EAGLE COPTERS CENTRO MANTENIMIENTO AUTORIZADO S.A.
A424: 76924298 | B424: INVERSIONES GARRIDO LÓPEZ LIMITADA
A425: 76928136 | B425: AGRICOLA ARBOLERA SPA
A426: 76928237 | B426: COMERCIALIZADORA FRANCISCO JAVIER SALAS POBLETE E.I.R.L.
A427: 76928632 | B427: CERTIFICACIONES GLOBAL LATINA CHILE SPA
A428: 76930718 | B428: INMOBILIARIA E INVERSIONES LOS ROBLES SA
A429: 76931010 | B429: COMERCIALIZADORA EMBALAJES COLCHAGUA LTDA
A430: 76931796 | B430: ROMERO Y SANCHEZ LTDA
A431: 76932001 | B431: POLIPLASTIC SPA
A432: 76934444 | B432: TRANSPORTE GAETE SPA
A433: 76951238 | B433: PRESTACIÓN DE SERVICIOS AGRICOLAS HÉCTOR EMILIO ROJAS ROA E.
A434: 76952545 | B434: MPM SPA
... A447: 76996251 | B447: MAQUINARIAS JEAN PAOLO PEREZ HERNANDEZ EMPRESA INDIVIDUAL DE
A448: 77.213.626 | B448: SOCIEDAD AGRICOLA SANTA IGNACIA LTDA
A449: 77005747 | B449: SOCIEDAD AGRICOLA Y TRANSPORTES NUNEZ OSORES LIMITADA
A450: 77006766 | B450: SOCIEDAD COM DE SERV TECNOLOGICOS LINTEC SPA
A451: 77026961 | B451: CREACIONES B Y L SPA
A452: 77032515 | B452: ATKINSON COSTABAL UNDURRAGA & ACHURRA LTDA
A453: 77036714 | B453: SERVICIOS AGRICOLAS S & P SPA
A454: 77036789 | B454: COMAGRO SPA
A455: 77038897 | B455: FERTIAMERICA SPA
A456: 77041976 | B456: TRANS-RADIO TELECOM SPA
A457: 77045207 | B457: AGRÍCOLA EL CAMPO VERDE LIMITADA
A458: 77049421 | B458: ATIPIRI SA
A459: 77049914 | B459: SERVICIOS AGRICOLAS MH SPA
A460: 77050916 | B460: SERVICIOS CAROLINA GONZALEZ PADILLA E.I.R.L.
... A737: 99596900 | B737: ICONTEC CHILE SPA
A738: EXP001 | B738: AGRICULTURAL CONSTRUCTION PARTS LLC.
