Workbook

Sheet Hoja1
A1: Código Cuenta | C1: Descripción Cuenta | D1: C.Costo | E1: P. Caja | F1: Código | G1: PROVEEDOR | H1: Tipo | I1: Número | J1: Inst. Financiero | K1: Debe | L1: Haber | M1: Descripción
A2: 2-1-02-02-03 | C2: Proveedores Nacionales | D2: 00000000 | E2: 0000000000 | F2: 76411321 | G2: =+VLOOKUP(F2,Hoja2!$A:$B,2,0) -> CGE S.A | H2: F3 | I2: 22937072 | J2: 00000000 | K2: 0 | L2: 3629790 | M2: F3/22937072 CGE S.A/SERVICIO ELECTRICO/CLIENTE-5481635
A3: 5-2-04-06-01 | C3: Electricidad | D3: 11060001 | E3: 0000000000 | F3: 76411321 | G3: =+VLOOKUP(F3,Hoja2!$A:$B,2,0) -> CGE S.A | H3: 00 | I3: 0 | J3: 00000000 | K3: 3061474 | L3: 0 | M3: F3/22937072 CGE S.A/SERVICIO ELECTRICO/CLIENTE-5481635
A4: 2-1-02-02-03 | C4: Proveedores Nacionales | D4: 00000000 | E4: 0000000000 | F4: 76411321 | G4: =+VLOOKUP(F4,Hoja2!$A:$B,2,0) -> CGE S.A | H4: F3 | I4: 22941620 | J4: 00000000 | K4: 0 | L4: 2071002 | M4: F3/22941620 CGE S.A/SERVICIO ELECTRICO/CLIENTE-1582722
A5: 5-2-04-06-01 | C5: Electricidad | D5: 11050001 | E5: 0000000000 | F5: 76411321 | G5: =+VLOOKUP(F5,Hoja2!$A:$B,2,0) -> CGE S.A | H5: 00 | I5: 0 | J5: 00000000 | K5: 1746210 | L5: 0 | M5: F3/22941620 CGE S.A/SERVICIO ELECTRICO/CLIENTE-1582722
A6: 2-1-02-02-03 | C6: Proveedores Nacionales | D6: 00000000 | E6: 0000000000 | F6: 77462311 | G6: =+VLOOKUP(F6,Hoja2!$A:$B,2,0) -> AGROMAQ SPA | H6: F3 | I6: 78 | J6: 00000000 | K6: 0 | L6: 1904000 | M6: F3/78 AGROMAQ/SERV TRACTORES/OC-3155
A7: 5-2-04-17-01 | C7: Servicio Arriendo Maquinaria | D7: 11050001 | E7: 0000000000 | F7: 77462311 | G7: =+VLOOKUP(F7,Hoja2!$A:$B,2,0) -> AGROMAQ SPA | H7: 00 | I7: 0 | J7: 00000000 | K7: 1600000 | L7: 0 | M7: F3/78 AGROMAQ/SERV TRACTORES/OC-3155
A8: 2-1-02-02-03 | C8: Proveedores Nacionales | D8: 00000000 | E8: 0000000000 | F8: 77079116 | G8: =+VLOOKUP(F8,Hoja2!$A:$B,2,0) -> MINIMACK SPA | H8: F3 | I8: 208 | J8: 00000000 | K8: 0 | L8: 214200 | M8: F3/208 MINIMACK/ TRASLADO TRACTOR/OC-3202
A9: 5-2-04-12-01 | C9: Fletes | D9: 11050001 | E9: 0000000000 | F9: 77079116 | G9: =+VLOOKUP(F9,Hoja2!$A:$B,2,0) -> MINIMACK SPA | H9: 00 | I9: 0 | J9: 00000000 | K9: 180000 | L9: 0 | M9: F3/208 MINIMACK/ TRASLADO TRACTOR/OC-3202
A10: 2-1-02-02-03 | C10: Proveedores Nacionales | D10: 00000000 | E10: 0000000000 | F10: 12413175 | G10: =+VLOOKUP(F10,Hoja2!$A:$B,2,0) -> JOANNA ISABEL RIQUELME TRUJILLO | H10: F3 | I10: 806 | J10: 00000000 | K10: 0 | L10: 137145 | M10: F3/806 JOANNA ISABEL RIQUELME/CONTROL PLAGAS DIC
A11: 5-2-04-07-01 | C11: Servicio de Aseo | D11: 11130001 | E11: 0000000000 | F11: 12413175 | G11: =+VLOOKUP(F11,Hoja2!$A:$B,2,0) -> JOANNA ISABEL RIQUELME TRUJILLO | H11: 00 | I11: 0 | J11: 00000000 | K11: 115248 | L11: 0 | M11: F3/806 JOANNA ISABEL RIQUELME/CONTROL PLAGAS DIC
A12: 2-1-02-02-03 | C12: Proveedores Nacionales | D12: 00000000 | E12: 0000000000 | F12: 76081128 | G12: =+VLOOKUP(F12,Hoja2!$A:$B,2,0) -> TRANSPORTES Y SERVICIOS BOZO &amp; BOZO LIMITADA | H12: F3 | I12: 2086 | J12: 00000000 | K12: 0 | L12: 30000 | M12: F3/2086 TRANSPORTES Y SERV BOZO &amp | N12: BOZO/REP NEUMATICO
A13: 5-2-03-05-02 | C13: Mant. y repuestos Maquinaria | D13: 11130001 | E13: 0000000000 | F13: 76081128 | G13: =+VLOOKUP(F13,Hoja2!$A:$B,2,0) -> TRANSPORTES Y SERVICIOS BOZO &amp; BOZO LIMITADA | H13: 00 | I13: 0 | J13: 00000000 | K13: 25210 | L13: 0 | M13: F3/2086 TRANSPORTES Y SERV BOZO &amp | N13: BOZO/REP NEUMATICO
A14: 2-1-02-02-03 | C14: Proveedores Nacionales | D14: 00000000 | E14: 0000000000 | F14: 77538629 | G14: =+VLOOKUP(F14,Hoja2!$A:$B,2,0) -> DISTRIBUIDORA VILLASECA SPA | H14: F3 | I14: 6385 | J14: 00000000 | K14: 0 | L14: 74000 | M14: F3/6385 DISTRIBUIDORA VILLASECA/AUTOGAS 15 KG
A15: 5-2-04-11-01 | C15: Gas | D15: 11050217 | E15: 0000000000 | F15: 77538629 | G15: =+VLOOKUP(F15,Hoja2!$A:$B,2,0) -> DISTRIBUIDORA VILLASECA SPA | H15: 00 | I15: 0 | J15: 00000000 | K15: 62185 | L15: 0 | M15: F3/6385 DISTRIBUIDORA VILLASECA/AUTOGAS 15 KG
A16: 2-1-02-02-03 | C16: Proveedores Nacionales | D16: 00000000 | E16: 0000000000 | F16: 77538629 | G16: =+VLOOKUP(F16,Hoja2!$A:$B,2,0) -> DISTRIBUIDORA VILLASECA SPA | H16: F3 | I16: 6399 | J16: 00000000 | K16: 0 | L16: 74000 | M16: F3/6399 DISTRIBUIDORA VILLASECA/AUTOGAS 15 KG
A17: 5-2-04-11-01 | C17: Gas | D17: 11050217 | E17: 0000000000 | F17: 77538629 | G17: =+VLOOKUP(F17,Hoja2!$A:$B,2,0) -> DISTRIBUIDORA VILLASECA SPA | H17: 00 | I17: 0 | J17: 00000000 | K17: 62185 | L17: 0 | M17: F3/6399 DISTRIBUIDORA VILLASECA/AUTOGAS 15 KG
A18: 2-1-02-02-03 | C18: Proveedores Nacionales | D18: 00000000 | E18: 0000000000 | F18: 76604898 | G18: =+VLOOKUP(F18,Hoja2!$A:$B,2,0) -> TECNOLOGIAS EN SEGURIDAD LTDA. | H18: F3 | I18: 6408 | J18: 00000000 | K18: 0 | L18: 178304 | M18: F3/6408 TECNOLOGIAS EN SEGURIDAD/SERV ALPHA
A19: 5-2-04-09-01 | C19: Seguridad | D19: 11130001 | E19: 0000000000 | F19: 76604898 | G19: =+VLOOKUP(F19,Hoja2!$A:$B,2,0) -> TECNOLOGIAS EN SEGURIDAD LTDA. | H19: 00 | I19: 0 | J19: 00000000 | K19: 149835 | L19: 0 | M19: F3/6408 TECNOLOGIAS EN SEGURIDAD/SERV ALPHA
A20: 2-1-02-02-03 | C20: Proveedores Nacionales | D20: 00000000 | E20: 0000000000 | F20: 77538629 | G20: =+VLOOKUP(F20,Hoja2!$A:$B,2,0) -> DISTRIBUIDORA VILLASECA SPA | H20: F3 | I20: 6412 | J20: 00000000 | K20: 0 | L20: 74000 | M20: F3/6412 DISTRIBUIDORA VILLASECA/AUTOGAS 15 KG
A21: 5-2-04-11-01 | C21: Gas | D21: 11050217 | E21: 0000000000 | F21: 77538629 | G21: =+VLOOKUP(F21,Hoja2!$A:$B,2,0) -> DISTRIBUIDORA VILLASECA SPA | H21: 00 | I21: 0 | J21: 00000000 | K21: 62185 | L21: 0 | M21: F3/6412 DISTRIBUIDORA VILLASECA/AUTOGAS 15 KG
A22: 2-1-02-02-03 | C22: Proveedores Nacionales | D22: 00000000 | E22: 0000000000 | F22: 76099405 | G22: =+VLOOKUP(F22,Hoja2!$A:$B,2,0) -> SERVICIOS DE CONECTIVIDAD RURAL SPA | H22: F3 | I22: 24436 | J22: 00000000 | K22: 0 | L22: 137148 | M22: F3/24436 SERVICIOS DE CONECTIVIDAD RURAL/INTERNET
A23: 5-2-04-01-01 | C23: Comunicaciones | D23: 11130001 | E23: 0000000000 | F23: 76099405 | G23: =+VLOOKUP(F23,Hoja2!$A:$B,2,0) -> SERVICIOS DE CONECTIVIDAD RURAL SPA | H23: 00 | I23: 0 | J23: 00000000 | K23: 115250 | L23: 0 | M23: F3/24436 SERVICIOS DE CONECTIVIDAD RURAL/INTERNET
A24: 2-1-02-02-03 | C24: Proveedores Nacionales | D24: 00000000 | E24: 0000000000 | F24: 97006000 | G24: =+VLOOKUP(F24,Hoja2!$A:$B,2,0) -> BANCO DE CREDITO E INVERSIONES | H24: F3 | I24: 27305221 | J24: 00000000 | K24: 0 | L24: 91431 | M24: F3/27305221 BANCO DE CREDITO E INV/COMISION MANT CTA CTE
A25: 5-3-01-02-02 | C25: Gastos Bancarios | D25: 00000000 | E25: 0000000000 | F25: 97006000 | G25: =+VLOOKUP(F25,Hoja2!$A:$B,2,0) -> BANCO DE CREDITO E INVERSIONES | H25: 00 | I25: 0 | J25: 00000000 | K25: 76833 | L25: 0 | M25: F3/27305221 BANCO DE CREDITO E INV/COMISION MANT CTA CTE
... A84: 5-2-03-01-01 | C84: Materiales de Oficina | D84: 11050001 | E84: 0000000000 | F84: 96556940 | G84: =+VLOOKUP(F84,Hoja2!$A:$B,2,0) -> PROVEEDORES INTEGRALES PRISA S.A | H84: 00 | I84: 0 | J84: 00000000 | K84: 69927 | L84: 0 | M84: F3/13649888 PROVEEDORES INTEGRALES PRISA/CUADERNO/OC-3236
A85: 2-1-02-02-03 | C85: Proveedores Nacionales | D85: 00000000 | E85: 0000000000 | F85: 76081128 | G85: =+VLOOKUP(F85,Hoja2!$A:$B,2,0) -> TRANSPORTES Y SERVICIOS BOZO &amp; BOZO LIMITADA | H85: F3 | I85: 2103 | J85: 00000000 | K85: 0 | L85: 44000 | M85: F3/2103 TRANSPORTES Y SERV BOZO &amp | N85: BOZO/REP NEUMATICO
A86: 5-2-03-05-02 | C86: Mant. y repuestos Maquinaria | D86: 11050001 | E86: 0000000000 | F86: 76081128 | G86: =+VLOOKUP(F86,Hoja2!$A:$B,2,0) -> TRANSPORTES Y SERVICIOS BOZO &amp; BOZO LIMITADA | H86: 00 | I86: 0 | J86: 00000000 | K86: 36975 | L86: 0 | M86: F3/2103 TRANSPORTES Y SERV BOZO &amp | N86: BOZO/REP NEUMATICO
A87: 2-1-02-02-03 | C87: Proveedores Nacionales | D87: 00000000 | E87: 0000000000 | F87: 76081128 | G87: =+VLOOKUP(F87,Hoja2!$A:$B,2,0) -> TRANSPORTES Y SERVICIOS BOZO &amp; BOZO LIMITADA | H87: F3 | I87: 2104 | J87: 00000000 | K87: 0 | L87: 41000 | M87: F3/2104 TRANSPORTES Y SERV BOZO &amp | N87: BOZO/VULCANIZADO
A88: 5-2-03-05-02 | C88: Mant. y repuestos Maquinaria | D88: 11050001 | E88: 0000000000 | F88: 76081128 | G88: =+VLOOKUP(F88,Hoja2!$A:$B,2,0) -> TRANSPORTES Y SERVICIOS BOZO &amp; BOZO LIMITADA | H88: 00 | I88: 0 | J88: 00000000 | K88: 34454 | L88: 0 | M88: F3/2104 TRANSPORTES Y SERV BOZO &amp | N88: BOZO/VULCANIZADO
A89: 2-1-02-02-03 | C89: Proveedores Nacionales | D89: 00000000 | E89: 0000000000 | F89: 77538629 | G89: =+VLOOKUP(F89,Hoja2!$A:$B,2,0) -> DISTRIBUIDORA VILLASECA SPA | H89: F3 | I89: 6524 | J89: 00000000 | K89: 0 | L89: 74000 | M89: F3/6524 DISTRIBUIDORA VILLASECA/ AUTOGAS 15 KG
A90: 5-2-04-11-01 | C90: Gas | D90: 11050217 | E90: 0000000000 | F90: 77538629 | G90: =+VLOOKUP(F90,Hoja2!$A:$B,2,0) -> DISTRIBUIDORA VILLASECA SPA | H90: 00 | I90: 0 | J90: 00000000 | K90: 62185 | L90: 0 | M90: F3/6524 DISTRIBUIDORA VILLASECA/ AUTOGAS 15 KG
A91: 2-1-02-02-03 | C91: Proveedores Nacionales | D91: 00000000 | E91: 0000000000 | F91: 77538629 | G91: =+VLOOKUP(F91,Hoja2!$A:$B,2,0) -> DISTRIBUIDORA VILLASECA SPA | H91: F3 | I91: 6533 | J91: 00000000 | K91: 0 | L91: 74000 | M91: F3/6533 DISTRIBUIDORA VILLASECA/ AUTOGAS 15 KG
A92: 5-2-04-11-01 | C92: Gas | D92: 11050217 | E92: 0000000000 | F92: 77538629 | G92: =+VLOOKUP(F92,Hoja2!$A:$B,2,0) -> DISTRIBUIDORA VILLASECA SPA | H92: 00 | I92: 0 | J92: 00000000 | K92: 62185 | L92: 0 | M92: F3/6533 DISTRIBUIDORA VILLASECA/ AUTOGAS 15 KG
A93: 2-1-02-02-03 | C93: Proveedores Nacionales | D93: 00000000 | E93: 0000000000 | F93: 97036000 | G93: =+VLOOKUP(F93,Hoja2!$A:$B,2,0) -> BANCO SANTANDER | H93: F4 | I93: 13200515 | J93: 00000000 | K93: 0 | L93: 1269 | M93: F4/13200515 BANCO SANTANDER/COMISION MANTENCION PLAN
A94: 5-3-01-02-02 | C94: Gastos Bancarios | D94: 00000000 | E94: 0000000000 | F94: 97036000 | G94: =+VLOOKUP(F94,Hoja2!$A:$B,2,0) -> BANCO SANTANDER | H94: 00 | I94: 0 | J94: 00000000 | K94: 1269 | L94: 0 | M94: F4/13200515 BANCO SANTANDER/COMISION MANTENCION PLAN
A95: 2-1-02-02-03 | C95: Proveedores Nacionales | D95: 00000000 | E95: 0000000000 | F95: 97036000 | G95: =+VLOOKUP(F95,Hoja2!$A:$B,2,0) -> BANCO SANTANDER | H95: F3 | I95: 50423021 | J95: 00000000 | K95: 0 | L95: 13636 | M95: F3/50423021 BANCO SANTANDER/COMISION MANTENCION PLAN
A96: 5-3-01-02-02 | C96: Gastos Bancarios | D96: 00000000 | E96: 0000000000 | F96: 97036000 | G96: =+VLOOKUP(F96,Hoja2!$A:$B,2,0) -> BANCO SANTANDER | H96: 00 | I96: 0 | J96: 00000000 | K96: 11458 | L96: 0 | M96: F3/50423021 BANCO SANTANDER/COMISION MANTENCION PLAN
A97: 2-1-02-02-03 | C97: Proveedores Nacionales | D97: 00000000 | E97: 0000000000 | F97: 77462311 | G97: =+VLOOKUP(F97,Hoja2!$A:$B,2,0) -> AGROMAQ SPA | H97: F3 | I97: 98 | J97: 00000000 | K97: 0 | L97: 1904000 | M97: F3/98 AGROMAQ/ SERV ARR TRACTORES/OC-3089
A98: 5-2-04-17-01 | C98: Servicio Arriendo Maquinaria | D98: 11050001 | E98: 0000000000 | F98: 77462311 | G98: =+VLOOKUP(F98,Hoja2!$A:$B,2,0) -> AGROMAQ SPA | H98: 00 | I98: 0 | J98: 00000000 | K98: 1600000 | L98: 0 | M98: F3/98 AGROMAQ/ SERV ARR TRACTORES/OC-3089
A99: 2-1-02-02-03 | C99: Proveedores Nacionales | D99: 00000000 | E99: 0000000000 | F99: 96565580 | G99: =+VLOOKUP(F99,Hoja2!$A:$B,2,0) -> CIA DE LEASING TATTERSALL S.A | H99: F4 | I99: 128278 | J99: 00000000 | K99: 0 | L99: 13400 | M99: F4/128278 CIA DE LEASING TATTERSALL/TAG VEHICULOS/OC-3232
A100: 5-2-05-05-03 | C100: Peajes y Estacionamientos | D100: 11130001 | E100: 0000000000 | F100: 96565580 | G100: =+VLOOKUP(F100,Hoja2!$A:$B,2,0) -> CIA DE LEASING TATTERSALL S.A | H100: 00 | I100: 0 | J100: 00000000 | K100: 13400 | L100: 0 | M100: F4/128278 CIA DE LEASING TATTERSALL/TAG VEHICULOS/OC-3232
... A712: 5-2-04-20-02 | C712: Licencias Informáticas | D712: 11050001 | E712: 00000000 | F712: 77133844 | G712: =+VLOOKUP(F712,Hoja2!$A:$B,2,0) -> AGROINVENTARIO SPA | H712: 00 | I712: 0 | J712: 00000000 | K712: 134334 | L712: 0 | M712: F3/1150 AGROINVENTARIO SPA/FEE MENSUAL AGOSTO
A713: 2-1-02-02-03 | C713: Proveedores Nacionales | D713: 00000000 | E713: 0000000000 | F713: 76081128 | G713: =+VLOOKUP(F713,Hoja2!$A:$B,2,0) -> TRANSPORTES Y SERVICIOS BOZO &amp; BOZO LIMITADA | H713: F3 | I713: 2304 | J713: 00000000 | K713: 0 | L713: 15000 | M713: F3/2304 TRANSPORTES Y SERVICIOS BOZO &amp | N713: BOZO/REP DE NEUMA
A714: 5-2-03-05-06 | C714: Mant. y repuestos Vehículos | D714: 11130001 | E714: 00000000 | F714: 76081128 | G714: =+VLOOKUP(F714,Hoja2!$A:$B,2,0) -> TRANSPORTES Y SERVICIOS BOZO &amp; BOZO LIMITADA | H714: 00 | I714: 0 | J714: 00000000 | K714: 12605 | L714: 0 | M714: F3/2304 TRANSPORTES Y SERVICIOS BOZO &amp | N714: BOZO/REP DE NEUMA
A715: 2-1-02-02-03 | C715: Proveedores Nacionales | D715: 00000000 | E715: 0000000000 | F715: 76081128 | G715: =+VLOOKUP(F715,Hoja2!$A:$B,2,0) -> TRANSPORTES Y SERVICIOS BOZO &amp; BOZO LIMITADA | H715: F3 | I715: 2307 | J715: 00000000 | K715: 0 | L715: 12000 | M715: F3/2307 TRANSPORTES Y SERVICIOS BOZO &amp | N715: BOZO/REP NEUMATIC
A716: 5-2-03-05-02 | C716: Mant. y repuestos Maquinaria | D716: 11130001 | E716: 00000000 | F716: 76081128 | G716: =+VLOOKUP(F716,Hoja2!$A:$B,2,0) -> TRANSPORTES Y SERVICIOS BOZO &amp; BOZO LIMITADA | H716: 00 | I716: 0 | J716: 00000000 | K716: 10084 | L716: 0 | M716: F3/2307 TRANSPORTES Y SERVICIOS BOZO &amp | N716: BOZO/REP NEUMATIC
A717: 2-1-02-02-03 | C717: Proveedores Nacionales | D717: 00000000 | E717: 0000000000 | F717: 76604898 | G717: =+VLOOKUP(F717,Hoja2!$A:$B,2,0) -> TECNOLOGIAS EN SEGURIDAD LTDA. | H717: F3 | I717: 7524 | J717: 00000000 | K717: 0 | L717: 182829 | M717: F3/7524 TECNOLOGIAS EN SEGURIDAD LTDA./SERV ALPHA 4 SEP
A718: 5-2-04-09-01 | C718: Seguridad | D718: 11130001 | E718: 00000000 | F718: 76604898 | G718: =+VLOOKUP(F718,Hoja2!$A:$B,2,0) -> TECNOLOGIAS EN SEGURIDAD LTDA. | H718: 00 | I718: 0 | J718: 00000000 | K718: 153638 | L718: 0 | M718: F3/7524 TECNOLOGIAS EN SEGURIDAD LTDA./SERV ALPHA 4 SEP
A719: 2-1-02-02-03 | C719: Proveedores Nacionales | D719: 00000000 | E719: 0000000000 | F719: 76604898 | G719: =+VLOOKUP(F719,Hoja2!$A:$B,2,0) -> TECNOLOGIAS EN SEGURIDAD LTDA. | H719: F3 | I719: 7602 | J719: 00000000 | K719: 0 | L719: 168766 | M719: F3/7602 TECNOLOGIAS EN SEGURIDAD LTDA./SERV ALPHA CUCHIPUY
A720: 5-2-04-09-01 | C720: Seguridad | D720: 11060001 | E720: 00000000 | F720: 76604898 | G720: =+VLOOKUP(F720,Hoja2!$A:$B,2,0) -> TECNOLOGIAS EN SEGURIDAD LTDA. | H720: 00 | I720: 0 | J720: 00000000 | K720: 141820 | L720: 0 | M720: F3/7602 TECNOLOGIAS EN SEGURIDAD LTDA./SERV ALPHA CUCHIPUY
A721: 2-1-02-02-03 | C721: Proveedores Nacionales | D721: 00000000 | E721: 0000000000 | F721: 76099405 | G721: =+VLOOKUP(F721,Hoja2!$A:$B,2,0) -> SERVICIOS DE CONECTIVIDAD RURAL SPA | H721: F3 | I721: 25750 | J721: 00000000 | K721: 0 | L721: 140597 | M721: F3/25750 SERVICIOS DE CONECTIVIDAD RURAL SPA/INTERNET AGOSTO
A722: 5-2-04-01-01 | C722: Comunicaciones | D722: 11130001 | E722: 00000000 | F722: 76099405 | G722: =+VLOOKUP(F722,Hoja2!$A:$B,2,0) -> SERVICIOS DE CONECTIVIDAD RURAL SPA | H722: 00 | I722: 0 | J722: 00000000 | K722: 118149 | L722: 0 | M722: F3/25750 SERVICIOS DE CONECTIVIDAD RURAL SPA/INTERNET AGOSTO
A723: 2-1-02-02-03 | C723: Proveedores Nacionales | D723: 00000000 | E723: 0000000000 | F723: 76502041 | G723: =+VLOOKUP(F723,Hoja2!$A:$B,2,0) -> MUNDO ETIQUETAS SPA | H723: F3 | I723: 36780 | J723: 00000000 | K723: 0 | L723: 106241 | M723: F3/36780 MUNDO ETIQUETAS SPA/CINTA TRANSFERENCIA RESINA
A724: 5-2-03-05-01 | C724: Insumos | D724: 11050001 | E724: 00000000 | F724: 76502041 | G724: =+VLOOKUP(F724,Hoja2!$A:$B,2,0) -> MUNDO ETIQUETAS SPA | H724: 00 | I724: 0 | J724: 00000000 | K724: 89278 | L724: 0 | M724: F3/36780 MUNDO ETIQUETAS SPA/CINTA TRANSFERENCIA RESINA
A725: 2-1-02-02-03 | C725: Proveedores Nacionales | D725: 00000000 | E725: 0000000000 | F725: 79736770 | G725: =+VLOOKUP(F725,Hoja2!$A:$B,2,0) -> COMERCIAL CALAMA S.A. | H725: F3 | I725: 86931 | J725: 00000000 | K725: 0 | L725: 950000 | M725: F3/86931 COMERCIAL CALAMA S.A./DIESEL COMBUSTIBLE
A726: 1-1-07-01-02 | C726: Impto. Petróleo Diésel (Ley 18.502) | D726: 00000000 | E726: 0000000000 | F726: 79736770 | G726: =+VLOOKUP(F726,Hoja2!$A:$B,2,0) -> COMERCIAL CALAMA S.A. | H726: 00 | I726: 0 | J726: 00000000 | K726: 122267 | L726: 0 | M726: F3/86931 COMERCIAL CALAMA S.A./DIESEL COMBUSTIBLE
A727: 2-1-02-02-03 | C727: Proveedores Nacionales | D727: 00000000 | E727: 0000000000 | F727: 96565580 | G727: =+VLOOKUP(F727,Hoja2!$A:$B,2,0) -> CIA DE LEASING TATTERSALL S.A | H727: F4 | I727: 136784 | J727: 00000000 | K727: 0 | L727: 900 | M727: F4/136784 CIA DE LEASING TATTERSALL S.A/TAG VEHICULOS
A728: 5-2-05-05-03 | C728: Peajes y Estacionamientos | D728: 11130001 | E728: 00000000 | F728: 96565580 | G728: =+VLOOKUP(F728,Hoja2!$A:$B,2,0) -> CIA DE LEASING TATTERSALL S.A | H728: 00 | I728: 0 | J728: 00000000 | K728: 900 | L728: 0 | M728: F4/136784 CIA DE LEASING TATTERSALL S.A/TAG VEHICULOS
... A1105: 5-3-01-02-02 | C1105: Gastos Bancarios | D1105: 00000000 | E1105: 00000000 | F1105: 97036000 | G1105: =+VLOOKUP(F1105,Hoja2!$A:$B,2,0) -> BANCO SANTANDER | H1105: 00 | I1105: 0 | J1105: 00000000 | K1105: 1309 | L1105: 0 | M1105: F4/14495901 BANCO SANTANDER/COM MANTENCION PLAN

Sheet CW202606265FBB
A1: COMPROBANTES INGRESADOS
A2: Moneda : 01 Peso Chileno
A3: Tipo : Todos
A4: Rango de Folios : Todos
A5: Fecha : 26/06/2026
A6: Norma: Tributaria e IFRS
A7: Area de Negocio: Todas
A9: Número | B9: Fecha | C9: Tipo | D9: N° Interno | E9: Estado | F9: Descripción
A10: Código Cuenta | C10: Descripción Cuenta | D10: Código | E10: Código | F10: Auxiliar | G10: Documento | I10: Det. de Gasto /
D11: C.Costo | E11: P. Caja | F11: Código | G11: Tipo | H11: Número | I11: Inst. Financiero | J11: Debe | K11: Haber | L11: Descripción
A13: 00000001 | B13: 08/01/2025 | C13: E | D13: 00000001 | E13: Vigente | F13: Pago proveedores $5.515.700
A14: 2-1-02-02-03 | C14: Proveedores Nacionales | D14: 00000000 | E14: 0000000000 | F14: 77512542 | G14: TR | H14: 8012025 | I14: 00000000 | J14: 4795700 | K14: 0 | L14: F-20
A15: 2-1-02-02-06 | C15: Honorarios Por Pagar | D15: 00000000 | E15: 0000000000 | F15: 18658379 | G15: TR | H15: 8012025 | I15: 00000000 | J15: 720000 | K15: 0 | L15: BH 30
A16: 1-1-01-02-02 | C16: Banco Santander $ | D16: 00000000 | E16: 0000000000 | F16: 0000000000 | G16: CB | H16: 8012025 | I16: 00000000 | J16: 0 | K16: 4795700 | L16: Pago proveedores $5.515.700
A17: 1-1-01-02-02 | C17: Banco Santander $ | D17: 00000000 | E17: 0000000000 | F17: 0000000000 | G17: CB | H17: 8012025 | I17: 00000000 | J17: 0 | K17: 720000 | L17: Pago proveedores $5.515.700
F19: Total Comprobante | J19: 5515700 | K19: 5515700
A21: 00000002 | B21: 17/01/2025 | C21: E | D21: 00000002 | E21: Vigente | F21: PAGO PROVEEDORES $2.738.578
A22: 2-1-02-02-03 | C22: Proveedores Nacionales | D22: 00000000 | E22: 0000000000 | F22: 71430300 | G22: CB | H22: 26072032 | I22: 00000000 | J22: 106624 | K22: 0 | L22: Pago: F3 43219 | M22: FUNDACION CHILENA DE CULTURA
A23: 2-1-02-02-03 | C23: Proveedores Nacionales | D23: 00000000 | E23: 0000000000 | F23: 76855237 | G23: CB | H23: 26072032 | I23: 00000000 | J23: 617001 | K23: 0 | L23: Pago: P1 59181 | M23: COMERCIAL TODO AGRO SPA
A24: 2-1-02-02-03 | C24: Proveedores Nacionales | D24: 00000000 | E24: 0000000000 | F24: 77079116 | G24: CB | H24: 26072032 | I24: 00000000 | J24: 583100 | K24: 0 | L24: Pago: F3 202 | M24: MINIMACK SPA
A25: 2-1-02-02-03 | C25: Proveedores Nacionales | D25: 00000000 | E25: 0000000000 | F25: 77538629 | G25: CB | H25: 26072032 | I25: 00000000 | J25: 37000 | K25: 0 | L25: Pago: F3 6237 | M25: DISTRIBUIDORA VILLASECA SPA
A26: 2-1-02-02-03 | C26: Proveedores Nacionales | D26: 00000000 | E26: 0000000000 | F26: 77538629 | G26: CB | H26: 26072032 | I26: 00000000 | J26: 74000 | K26: 0 | L26: Pago: F3 6241 | M26: DISTRIBUIDORA VILLASECA SPA
A27: 2-1-02-02-03 | C27: Proveedores Nacionales | D27: 00000000 | E27: 0000000000 | F27: 78866720 | G27: CB | H27: 26072032 | I27: 00000000 | J27: 271082 | K27: 0 | L27: Pago: F3 922539 | M27: INVERSIONES Y COMERCIAL TRANCURA LIMITADA
A28: 2-1-02-02-03 | C28: Proveedores Nacionales | D28: 00000000 | E28: 0000000000 | F28: 79736770 | G28: CB | H28: 26072032 | I28: 00000000 | J28: 922000 | K28: 0 | L28: Pago: F3 78696 | M28: COMERCIAL CALAMA S.A.
A29: 2-1-02-02-03 | C29: Proveedores Nacionales | D29: 00000000 | E29: 0000000000 | F29: 91502000 | G29: CB | H29: 26072032 | I29: 00000000 | J29: 127771 | K29: 0 | L29: Pago: F3 4619581 | M29: SALINAS Y FABRES S.A.
A30: 1-1-01-02-06 | C30: Banco BCI $ | D30: 00000000 | E30: 0000000000 | F30: 0000000000 | G30: CB | H30: 17012025 | I30: 00000000 | J30: 0 | K30: 2738578 | L30: CB 17012025 | M30: Pago varios proveedores
F32: Total Comprobante | J32: 2738578 | K32: 2738578
A34: 00000003 | B34: 13/01/2025 | C34: E | D34: 00000003 | E34: Vigente | F34: Pago CGE $3.629.800
A35: 1-1-01-02-02 | C35: Banco Santander $ | D35: 00000000 | E35: 0000000000 | F35: 0000000000 | G35: CB | H35: 13012025 | I35: 00000000 | J35: 0 | K35: 3629800 | L35: Pago CGE $3.629.800
A36: 2-1-02-02-03 | C36: Proveedores Nacionales | D36: 00000000 | E36: 0000000000 | F36: 76411321 | G36: TR | H36: 13012025 | I36: 00000000 | J36: 3629790 | K36: 0 | L36: F-22937072
A37: 5-2-04-06-01 | C37: Electricidad | D37: 11050001 | E37: 0000000000 | F37: 0000000000 | G37: 00 | H37: 0 | I37: 00000000 | J37: 10 | K37: 0 | L37: Ajuste pago $3.629.800
F39: Total Comprobante | J39: 3629800 | K39: 3629800
A41: 00000004 | B41: 13/01/2025 | C41: E | D41: 00000004 | E41: Vigente | F41: Pago CGE $2.071.000
A42: 1-1-01-02-02 | C42: Banco Santander $ | D42: 00000000 | E42: 0000000000 | F42: 0000000000 | G42: CB | H42: 13012025 | I42: 00000000 | J42: 0 | K42: 2071000 | L42: Pago CGE $2.071.000
A43: 2-1-02-02-03 | C43: Proveedores Nacionales | D43: 00000000 | E43: 0000000000 | F43: 76411321 | G43: TR | H43: 13012025 | I43: 00000000 | J43: 2071002 | K43: 0 | L43: F-22941620
A44: 5-2-04-06-01 | C44: Electricidad | D44: 11050001 | E44: 0000000000 | F44: 0000000000 | G44: 00 | H44: 0 | I44: 00000000 | J44: 0 | K44: 2 | L44: Ajuste pago $2.071.000
F46: Total Comprobante | J46: 2071002 | K46: 2071002
A48: 00000005 | B48: 10/01/2025 | C48: T | D48: 00000001 | E48: Vigente | F48: F3/22937072/CGE S.A
A49: 2-1-02-02-03 | C49: Proveedores Nacionales | D49: 00000000 | E49: 0000000000 | F49: 76411321 | G49: F3 | H49: 22937072 | I49: 00000000 | J49: 0 | K49: 3629790 | L49: F3/22937072 CGE S.A/SERVICIO ELECTRICO/CLIENTE-5481635
A50: 1-1-07-01-01 | C50: IVA Crédito Fiscal | D50: 00000000 | E50: 0000000000 | F50: 0000000000 | G50: 00 | H50: 0 | I50: 00000000 | J50: 568316 | K50: 0 | L50: F3/22937072 CGE S.A/SERVICIO ELECTRICO/CLIENTE-5481635
A51: 5-2-04-06-01 | C51: Electricidad | D51: 11060001 | E51: 0000000000 | F51: 0000000000 | G51: 00 | H51: 0 | I51: 00000000 | J51: 3061474 | K51: 0 | L51: F3/22937072 CGE S.A/SERVICIO ELECTRICO/CLIENTE-5481635
F53: Total Comprobante | J53: 3629790 | K53: 3629790
A55: 00000006 | B55: 10/01/2025 | C55: T | D55: 00000002 | E55: Vigente | F55: F3/22941620/CGE S.A
A56: 2-1-02-02-03 | C56: Proveedores Nacionales | D56: 00000000 | E56: 0000000000 | F56: 76411321 | G56: F3 | H56: 22941620 | I56: 00000000 | J56: 0 | K56: 2071002 | L56: F3/22941620 CGE S.A/SERVICIO ELECTRICO/CLIENTE-1582722
A57: 1-1-07-01-01 | C57: IVA Crédito Fiscal | D57: 00000000 | E57: 0000000000 | F57: 0000000000 | G57: 00 | H57: 0 | I57: 00000000 | J57: 324792 | K57: 0 | L57: F3/22941620 CGE S.A/SERVICIO ELECTRICO/CLIENTE-1582722
A58: 5-2-04-06-01 | C58: Electricidad | D58: 11050001 | E58: 0000000000 | F58: 0000000000 | G58: 00 | H58: 0 | I58: 00000000 | J58: 1746210 | K58: 0 | L58: F3/22941620 CGE S.A/SERVICIO ELECTRICO/CLIENTE-1582722
F60: Total Comprobante | J60: 2071002 | K60: 2071002
A62: 00000007 | B62: 13/01/2025 | C62: T | D62: 00000003 | E62: Vigente | F62: F3/78/AGROMAQ SPA
A63: 2-1-02-02-03 | C63: Proveedores Nacionales | D63: 00000000 | E63: 0000000000 | F63: 77462311 | G63: F3 | H63: 78 | I63: 00000000 | J63: 0 | K63: 1904000 | L63: F3/78 AGROMAQ/SERV TRACTORES/OC-3155
A64: 1-1-07-01-01 | C64: IVA Crédito Fiscal | D64: 00000000 | E64: 0000000000 | F64: 0000000000 | G64: 00 | H64: 0 | I64: 00000000 | J64: 304000 | K64: 0 | L64: F3/78 AGROMAQ/SERV TRACTORES/OC-3155
A65: 5-2-04-17-01 | C65: Servicio Arriendo Maquinaria | D65: 11050001 | E65: 0000000000 | F65: 0000000000 | G65: 00 | H65: 0 | I65: 00000000 | J65: 1600000 | K65: 0 | L65: F3/78 AGROMAQ/SERV TRACTORES/OC-3155
F67: Total Comprobante | J67: 1904000 | K67: 1904000
A69: 00000008 | B69: 13/01/2025 | C69: T | D69: 00000004 | E69: Vigente | F69: F3/208/MINIMACK SPA
A70: 2-1-02-02-03 | C70: Proveedores Nacionales | D70: 00000000 | E70: 0000000000 | F70: 77079116 | G70: F3 | H70: 208 | I70: 00000000 | J70: 0 | K70: 214200 | L70: F3/208 MINIMACK/ TRASLADO TRACTOR/OC-3202
A71: 1-1-07-01-01 | C71: IVA Crédito Fiscal | D71: 00000000 | E71: 0000000000 | F71: 0000000000 | G71: 00 | H71: 0 | I71: 00000000 | J71: 34200 | K71: 0 | L71: F3/208 MINIMACK/ TRASLADO TRACTOR/OC-3202
A72: 5-2-04-12-01 | C72: Fletes | D72: 11050001 | E72: 0000000000 | F72: 0000000000 | G72: 00 | H72: 0 | I72: 00000000 | J72: 180000 | K72: 0 | L72: F3/208 MINIMACK/ TRASLADO TRACTOR/OC-3202
F74: Total Comprobante | J74: 214200 | K74: 214200
A76: 00000009 | B76: 13/01/2025 | C76: T | D76: 00000005 | E76: Vigente | F76: F3/806/JOANNA ISABEL RIQUELME TRUJILLO
A77: 2-1-02-02-03 | C77: Proveedores Nacionales | D77: 00000000 | E77: 0000000000 | F77: 12413175 | G77: F3 | H77: 806 | I77: 00000000 | J77: 0 | K77: 137145 | L77: F3/806 JOANNA ISABEL RIQUELME/CONTROL PLAGAS DIC
A78: 1-1-07-01-01 | C78: IVA Crédito Fiscal | D78: 00000000 | E78: 0000000000 | F78: 0000000000 | G78: 00 | H78: 0 | I78: 00000000 | J78: 21897 | K78: 0 | L78: F3/806 JOANNA ISABEL RIQUELME/CONTROL PLAGAS DIC
A79: 5-2-04-07-01 | C79: Servicio de Aseo | D79: 11130001 | E79: 0000000000 | F79: 0000000000 | G79: 00 | H79: 0 | I79: 00000000 | J79: 115248 | K79: 0 | L79: F3/806 JOANNA ISABEL RIQUELME/CONTROL PLAGAS DIC
F81: Total Comprobante | J81: 137145 | K81: 137145
A83: 00000010 | B83: 13/01/2025 | C83: T | D83: 00000006 | E83: Vigente | F83: F3/2086/TRANSPORTES Y SERVICIOS BOZO &amp | G83: BOZO LIMITADA
A84: 2-1-02-02-03 | C84: Proveedores Nacionales | D84: 00000000 | E84: 0000000000 | F84: 76081128 | G84: F3 | H84: 2086 | I84: 00000000 | J84: 0 | K84: 30000 | L84: F3/2086 TRANSPORTES Y SERV BOZO &amp | M84: BOZO/REP NEUMATICO
A85: 1-1-07-01-01 | C85: IVA Crédito Fiscal | D85: 00000000 | E85: 0000000000 | F85: 0000000000 | G85: 00 | H85: 0 | I85: 00000000 | J85: 4790 | K85: 0 | L85: F3/2086 TRANSPORTES Y SERV BOZO &amp | M85: BOZO/REP NEUMATICO
A86: 5-2-03-05-02 | C86: Mant. y repuestos Maquinaria | D86: 11130001 | E86: 0000000000 | F86: 0000000000 | G86: 00 | H86: 0 | I86: 00000000 | J86: 25210 | K86: 0 | L86: F3/2086 TRANSPORTES Y SERV BOZO &amp | M86: BOZO/REP NEUMATICO
F88: Total Comprobante | J88: 30000 | K88: 30000
A90: 00000011 | B90: 13/01/2025 | C90: T | D90: 00000007 | E90: Vigente | F90: F3/6385/DISTRIBUIDORA VILLASECA SPA
A91: 2-1-02-02-03 | C91: Proveedores Nacionales | D91: 00000000 | E91: 0000000000 | F91: 77538629 | G91: F3 | H91: 6385 | I91: 00000000 | J91: 0 | K91: 74000 | L91: F3/6385 DISTRIBUIDORA VILLASECA/AUTOGAS 15 KG
A92: 1-1-07-01-01 | C92: IVA Crédito Fiscal | D92: 00000000 | E92: 0000000000 | F92: 0000000000 | G92: 00 | H92: 0 | I92: 00000000 | J92: 11815 | K92: 0 | L92: F3/6385 DISTRIBUIDORA VILLASECA/AUTOGAS 15 KG
A93: 5-2-04-11-01 | C93: Gas | D93: 11050217 | E93: 0000000000 | F93: 0000000000 | G93: 00 | H93: 0 | I93: 00000000 | J93: 62185 | K93: 0 | L93: F3/6385 DISTRIBUIDORA VILLASECA/AUTOGAS 15 KG
F95: Total Comprobante | J95: 74000 | K95: 74000
A97: 00000012 | B97: 13/01/2025 | C97: T | D97: 00000008 | E97: Vigente | F97: F3/6399/DISTRIBUIDORA VILLASECA SPA
A98: 2-1-02-02-03 | C98: Proveedores Nacionales | D98: 00000000 | E98: 0000000000 | F98: 77538629 | G98: F3 | H98: 6399 | I98: 00000000 | J98: 0 | K98: 74000 | L98: F3/6399 DISTRIBUIDORA VILLASECA/AUTOGAS 15 KG
A99: 1-1-07-01-01 | C99: IVA Crédito Fiscal | D99: 00000000 | E99: 0000000000 | F99: 0000000000 | G99: 00 | H99: 0 | I99: 00000000 | J99: 11815 | K99: 0 | L99: F3/6399 DISTRIBUIDORA VILLASECA/AUTOGAS 15 KG
A100: 5-2-04-11-01 | C100: Gas | D100: 11050217 | E100: 0000000000 | F100: 0000000000 | G100: 00 | H100: 0 | I100: 00000000 | J100: 62185 | K100: 0 | L100: F3/6399 DISTRIBUIDORA VILLASECA/AUTOGAS 15 KG
F102: Total Comprobante | J102: 74000 | K102: 74000
A104: 00000013 | B104: 13/01/2025 | C104: T | D104: 00000009 | E104: Vigente | F104: F3/6408/TECNOLOGIAS EN SEGURIDAD LTDA.
A105: 2-1-02-02-03 | C105: Proveedores Nacionales | D105: 00000000 | E105: 0000000000 | F105: 76604898 | G105: F3 | H105: 6408 | I105: 00000000 | J105: 0 | K105: 178304 | L105: F3/6408 TECNOLOGIAS EN SEGURIDAD/SERV ALPHA
A106: 1-1-07-01-01 | C106: IVA Crédito Fiscal | D106: 00000000 | E106: 0000000000 | F106: 0000000000 | G106: 00 | H106: 0 | I106: 00000000 | J106: 28469 | K106: 0 | L106: F3/6408 TECNOLOGIAS EN SEGURIDAD/SERV ALPHA
A107: 5-2-04-09-01 | C107: Seguridad | D107: 11130001 | E107: 0000000000 | F107: 0000000000 | G107: 00 | H107: 0 | I107: 00000000 | J107: 149835 | K107: 0 | L107: F3/6408 TECNOLOGIAS EN SEGURIDAD/SERV ALPHA
F109: Total Comprobante | J109: 178304 | K109: 178304
A111: 00000014 | B111: 13/01/2025 | C111: T | D111: 00000010 | E111: Vigente | F111: F3/6412/DISTRIBUIDORA VILLASECA SPA
A112: 2-1-02-02-03 | C112: Proveedores Nacionales | D112: 00000000 | E112: 0000000000 | F112: 77538629 | G112: F3 | H112: 6412 | I112: 00000000 | J112: 0 | K112: 74000 | L112: F3/6412 DISTRIBUIDORA VILLASECA/AUTOGAS 15 KG
A113: 1-1-07-01-01 | C113: IVA Crédito Fiscal | D113: 00000000 | E113: 0000000000 | F113: 0000000000 | G113: 00 | H113: 0 | I113: 00000000 | J113: 11815 | K113: 0 | L113: F3/6412 DISTRIBUIDORA VILLASECA/AUTOGAS 15 KG
A114: 5-2-04-11-01 | C114: Gas | D114: 11050217 | E114: 0000000000 | F114: 0000000000 | G114: 00 | H114: 0 | I114: 00000000 | J114: 62185 | K114: 0 | L114: F3/6412 DISTRIBUIDORA VILLASECA/AUTOGAS 15 KG
F116: Total Comprobante | J116: 74000 | K116: 74000
A118: 00000015 | B118: 13/01/2025 | C118: T | D118: 00000011 | E118: Vigente | F118: F3/24436/SERVICIOS DE CONECTIVIDAD RURAL SPA
A119: 2-1-02-02-03 | C119: Proveedores Nacionales | D119: 00000000 | E119: 0000000000 | F119: 76099405 | G119: F3 | H119: 24436 | I119: 00000000 | J119: 0 | K119: 137148 | L119: F3/24436 SERVICIOS DE CONECTIVIDAD RURAL/INTERNET
A120: 1-1-07-01-01 | C120: IVA Crédito Fiscal | D120: 00000000 | E120: 0000000000 | F120: 0000000000 | G120: 00 | H120: 0 | I120: 00000000 | J120: 21898 | K120: 0 | L120: F3/24436 SERVICIOS DE CONECTIVIDAD RURAL/INTERNET
A121: 5-2-04-01-01 | C121: Comunicaciones | D121: 11130001 | E121: 0000000000 | F121: 0000000000 | G121: 00 | H121: 0 | I121: 00000000 | J121: 115250 | K121: 0 | L121: F3/24436 SERVICIOS DE CONECTIVIDAD RURAL/INTERNET
F123: Total Comprobante | J123: 137148 | K123: 137148
A125: 00000016 | B125: 13/01/2025 | C125: T | D125: 00000012 | E125: Vigente | F125: F6/656937/TATTERSALL AGROINSUMOS S.A.
A126: 2-1-02-02-03 | C126: Proveedores Nacionales | D126: 00000000 | E126: 0000000000 | F126: 96775400 | G126: F6 | H126: 656937 | I126: 00000000 | J126: 0 | K126: 2371575 | L126: F6/656937 TATTERSALL AGROINSUMOS/ FASCINATE/OC-3200
A127: 1-1-07-01-01 | C127: IVA Crédito Fiscal | D127: 00000000 | E127: 0000000000 | F127: 0000000000 | G127: 00 | H127: 0 | I127: 00000000 | J127: 378655 | K127: 0 | L127: F3/656937 TATTERSALL AGROINSUMOS/ FASCINATE/OC-3200
A128: 1-1-08-01-02 | C128: Materiales e Insumos | D128: 00000000 | E128: 0000000000 | F128: 0000000000 | G128: 00 | H128: 0 | I128: 00000000 | J128: 1992920 | K128: 0 | L128: F3/656937 TATTERSALL AGROINSUMOS/ FASCINATE/OC-3200
F130: Total Comprobante | J130: 2371575 | K130: 2371575
A132: 00000017 | B132: 13/01/2025 | C132: T | D132: 00000013 | E132: Vigente | F132: F6/658465/TATTERSALL AGROINSUMOS S.A.
A133: 2-1-02-02-03 | C133: Proveedores Nacionales | D133: 00000000 | E133: 0000000000 | F133: 96775400 | G133: F6 | H133: 658465 | I133: 00000000 | J133: 0 | K133: 239787 | L133: F6/658465 TATTERSALL AGROINSUMOS/SPRINGER/OC-3209
A134: 1-1-07-01-01 | C134: IVA Crédito Fiscal | D134: 00000000 | E134: 0000000000 | F134: 0000000000 | G134: 00 | H134: 0 | I134: 00000000 | J134: 38285 | K134: 0 | L134: F3/658465 TATTERSALL AGROINSUMOS/SPRINGER/OC-3209
...

Sheet Hoja2
A1: Código | B1: Razón social
A2: 10049125 | B2: JOSE SANDRO CARRASCO URETA
A3: 10131083 | B3: JUAN MANUEL MORALES VERGARA
A4: 10158144 | B4: VICENTE ALEJANDRO PINA URZUA
A5: 10162014 | B5: ALFONSO GONZALO VALENZUELA CORREA
A6: 10274720 | B6: PAULO JOSE AMADO ROMO
A7: 10300064 | B7: JUAN ALEXIS REYES SEGURA
A8: 10302821 | B8: MARINA DEL CARMEN SEPULVEDA BARAHONA
A9: 10347469 | B9: PABLO MAGNASCO VASQUEZ
A10: 10427844 | B10: LUIS ARTURO LIZANA PENA
A11: 10435173 | B11: DINO FRANCO PEÑALOZA MOLINA
A12: 10453671 | B12: MANUEL JESUS VALDES ACEVEDO
A13: 10460642 | B13: JOSE RODRIGO PAVEZ MORENO
... A20: 10898803 | B20: MARIA ANDREA PIZARRO VELIZ
A21: 10927072CT | B21: PAOLA ANDREA ESCOBAR BURGOS
A22: 10940143CT | B22: MARIA LUISA PONCE SEPULVEDA
A23: 10975553 | B23: CLAUDIA MATUS GATICA
A24: 11057106 | B24: MAGALY DEL CARMEN RIVERA CANTILLANA
A25: 11143836 | B25: ALEX ANTONIO FUENZALIDA NUÑEZ
A26: 11277337 | B26: RAFAEL PATRICIO PINA CAMPOS
A27: 11283655 | B27: LUIS IVAN CORDERO CASTRO
A28: 11484217 | B28: LUISA MEDINA
A29: 11528751 | B29: JOSE HERNAN PLAZA GALLARDO
A30: 11551345 | B30: HUGO ERNESTO HENRIQUEZ LASTRA
A31: 11554940 | B31: LUIS GUILLERMO PEÑA VALDES
A32: 11555517 | B32: SOLERCIO ANTONIO PASTENE TORRES
A33: 11562253 | B33: MARIA INES FAUNDEZ GUAJARDO
A34: 11759075 | B34: ULISES RODRIGUEZ ZAMORANO
... A44: 12695363 | B44: David Soto Contreras
A45: 12725734CT | B45: SUSSY ALEJANDRA ASTORGA RIVERAS
A46: 12865813 | B46: FERNANDA LUZ ORTIZ VELIZ
A47: 12912271 | B47: RODRIGO ALFONSO ALARCON CORRALES
A48: 12963368 | B48: PABLO ANDRES CONTRERAS VASQUEZ
A49: 13099763 | B49: JOSE MANUEL ARIAS MEJIAS
A50: 13100069 | B50: CARLOS ECHAGUE PAVEZ
A51: 13100102 | B51: AMERICO ZUÑIGA
A52: 13346006 | B52: JUAN PABLO REYES FUENTES
A53: 13375769 | B53: FARY ENOC PARADA VARGAS
A54: 13476990 | B54: MARCELA JORQUERA OYARCE
A55: 13501829 | B55: LUIS HERNAN NUNEZ MORA
A56: 13505376 | B56: MARIANA JOCELYN VASQUEZ RODRIGUEZ
A57: 13561123 | B57: JORGE LUIS LIZANA CACERES
... A116: 18658379 | B116: JOSE MIGUEL RUBIO RODRIGUEZ
A117: 19210510CT | B117: CARLOS FELIPE MORENO LABRA
A118: 19589881 | B118: SEBASTIAN JOSE CARLOS QUILODRAN SOTO
A119: 19749814 | B119: JOSE ARAYA
A120: 20024951 | B120: CAROLINA MUÑOZ ESPINOZA
A121: 20039798 | B121: Daniela Catalina Valenzuela Jaque
A122: 20602511 | B122: ROCIO BELEN SALINAS SOTO
A123: 21583947 | B123: AGUSTIN ALEXIS GALVEZ CADIZ
A124: 21854252 | B124: CARLOS EDUARDO PRADO SALAS
A125: 22304863 | B125: Angel Manuel Navarrete Zepeda
A126: 4457613 | B126: ANATOLIO JOSE RAMIREZ VALENZUELA
A127: 4458456 | B127: MARIA ANGELICA FARIAS LOPEZ
A128: 4822813 | B128: GLORIA MAGALY ISBEJ ATAL
A129: 52004583 | B129: EMPRESA COMERCIALIZADORA EDUARDO ORELLANA ESPINOZA E I R L
... A172: 76031716 | B172: Trivar Helicopteros Asesorias e Inversiones Spa
A173: 76033621CT | B173: AGRICOLA Y COMERCIAL EL TREBOL SPA
A174: 76039218 | B174: SERVICIO ADR LTDA.
A175: 76040476 | B175: COMERCIALIZADORA VIVERO CORCOLEN
A176: 76046889 | B176: MARTINEZ Y VALDIVIESO S.A
A177: 76048145 | B177: COMERCIALIZADORA DE ENVASES INDUSTRIALES LTDA
A178: 76049842 | B178: INVERSIONES JULIAN LTDA
A179: 76050259 | B179: AGROVAL, SERVICIOS E.I.R.L.
A180: 76052927 | B180: Soc. Conc. Autopista Nueva Vespucio Sur S.A.
A181: 76060852 | B181: SOCIEDAD COMERCIAL ELECTROFERR S.A.
A182: 76061483 | B182: SOCIEDAD DE SERVICIOS PIA Y COMPANIA LIMITADA
A183: 76062494 | B183: SYSTECH CHILE LIMITADA
A184: 76068396 | B184: ECO PLASTICOS SPA
A185: 76072472 | B185: FACTORING BANINTER S.A
... A358: 76921928 | B358: AGROUTIL MARIA JOSE UGARTE TAPIA E.I.R.L.
A359: 76921928CT | B359: AGROUTIL MARIA JOSE UGARTE TAPIA E.I.R.L.
A360: 76924298 | B360: INVERSIONES GARRIDO LÓPEZ LIMITADA
A361: 76928136 | B361: AGRICOLA ARBOLERA SPA
A362: 769300718 | B362: INMOBILIARIA E INVERSIONES LOS ROBLES S.A
A363: 76930718 | B363: INMOBILIARIA E INVERSIONES LOS ROBLES S.A.
A364: 76931010 | B364: COMERCIALIZADORA EMBALAJES COLCHAGUA LTDA
A365: 76941075 | B365: SUPERFRUTA SPA
A366: 76951238 | B366: PRESTACIÓN DE SERVICIOS AGRICOLAS HÉCTOR EMILIO ROJAS ROA E.
A367: 76952545 | B367: MPM SPA
A368: 76955220 | B368: IMPORTADORA Y EXPORTADORA RIO EBRO
A369: 76955503 | B369: FERRETERIA MADARIAGA LIMITADA
A370: 76957224 | B370: IMPRENTA FIRGRAF SPA
A371: 76962383 | B371: SOCIEDAD COMERCIALIZADORA ROCO LIMITADA
... A640: 99575550 | B640: BOLSA DE PRODUC. DE CHILE
